[{"Translation":"The little yellow place","gridref":"NN 660 776","height":936.0,"lat":56.870392,"lon":-4.199976,"name":"A' Bhuidheanach Bheag","number":"M240","range":"None"},{"Translation":"The old woman","gridref":"NH 681 041","height":930.0,"lat":57.108879,"lon":-4.179417,"name":"A' Chailleach","number":"M251","range":"None"},{"Translation":"The old woman","gridref":"NH 136 714","height":997.0,"lat":57.693669,"lon":-5.1290651,"name":"A' Chailleach","number":"M144","range":"Loch Fannich"},{"Translation":"The basket or creel","gridref":"NH 094 148","height":1120.0,"lat":57.184277,"lon":-5.1553615,"name":"A' Chralaig","number":"M033","range":"None"},{"Translation":"The greenish-grey hill","gridref":"NH 008 230","height":918.0,"lat":57.25416,"lon":-5.30397,"name":"A' Ghlas-bheinn","number":"M274","range":"None"},{"Translation":"The maiden","gridref":"NH 007 749","height":967.0,"lat":57.719523,"lon":-5.3479901,"name":"A' Mhaighdean","number":"M187","range":"Fisherfield Forest"},{"Translation":"The horse place","gridref":"NN 604 762","height":975.0,"lat":56.856175,"lon":-4.290997,"name":"A' Mharconaich","number":"M179","range":"None"},{"Translation":null,"gridref":"NN 735 807","height":875.0,"lat":56.9003316177,"lon":-4.0793246663,"name":"A'Chaoirnich [Maol Creag an Loch]","number":"C078","range":"None"},{"Translation":null,"gridref":"NM 378 943","height":781.0,"lat":56.9653378006,"lon":-6.3220963518,"name":"Ainshval","number":"C235","range":"None"},{"Translation":"Obscure, but probably NOT the executioner","gridref":"NG 465 253","height":934.0,"lat":57.247915,"lon":-6.2040405,"name":"Am Basteir","number":"M242","range":"Black Cuilin"},{"Translation":null,"gridref":"NH 073 143","height":798.0,"lat":57.1789180668,"lon":-5.1923902368,"name":"Am Bathach","number":"C172","range":"None"},{"Translation":"The old man","gridref":"NN 176 650","height":1032.0,"lat":56.740859,"lon":-4.9839425,"name":"Am Bodach","number":"M099","range":"Mamores"},{"Translation":"The place of the shells","gridref":"NH 303 793","height":953.0,"lat":57.771153,"lon":-4.8548723,"name":"Am Faochagach","number":"M210","range":"None"},{"Translation":"The castle","gridref":"NN 378 193","height":995.0,"lat":56.338195,"lon":-4.6255291,"name":"An Caisteal","number":"M147","range":"Loch Lomond; Crianlarich"},{"Translation":null,"gridref":"NB 154 073","height":799.0,"lat":57.9636498771,"lon":-6.823458092,"name":"An Cliseam [Clisham]","number":"C243","range":"None"},{"Translation":"The little cock","gridref":"NH 241 680","height":923.0,"lat":57.6674,"lon":-4.950691,"name":"An Coileachan","number":"M266","range":"Loch Fannich"},{"Translation":null,"gridref":"NN 716 801","height":827.0,"lat":56.8944226909,"lon":-4.1102263316,"name":"An Dun","number":"C074","range":"None"},{"Translation":null,"gridref":"NN 717 805","height":827.0,"lat":56.8980412976,"lon":-4.1087867569,"name":"An Dun","number":"C073","range":"None"},{"Translation":"The complainer","gridref":"NN 187 669","height":982.0,"lat":56.758334,"lon":-4.9673291,"name":"An Gearanach","number":"M166","range":"Mamores"},{"Translation":"The brindled greyish one","gridref":"NH 133 344","height":1129.0,"lat":57.361687,"lon":-5.1057191,"name":"An Riabhachan","number":"M029","range":"Loch Mullardoch"},{"Translation":null,"gridref":"NG 921 480","height":892.0,"lat":57.4744506369,"lon":-5.4725455919,"name":"An Ruadh-stac","number":"C196","range":"None"},{"Translation":"The place of the sharp rocks","gridref":"NN 933 836","height":1006.0,"lat":56.931351,"lon":-3.7548964,"name":"An Sgarsoch","number":"M125","range":"None"},{"Translation":null,"gridref":"NH 171 453","height":814.0,"lat":57.4610040359,"lon":-5.0531651017,"name":"An Sidhean","number":"C182","range":"None"},{"Translation":"The projecting place (beak or snout)","gridref":"NO 079 799","height":944.0,"lat":56.901261,"lon":-3.5137491,"name":"An Socach","number":"M227","range":"None"},{"Translation":"The snout","gridref":"NH 088 230","height":921.0,"lat":57.257574,"lon":-5.1715825,"name":"An Socach","number":"M269","range":"None"},{"Translation":"The projecting place, or snout","gridref":"NH 100 332","height":1069.0,"lat":57.34956,"lon":-5.1595648,"name":"An Socach","number":"M067","range":"Loch Mullardoch"},{"Translation":null,"gridref":"NM 762 792","height":814.0,"lat":56.8501473227,"lon":-5.6760136056,"name":"An Stac","number":"C125","range":"None"},{"Translation":"the peak","gridref":"NN 639 431","height":1118.0,"lat":56.56008,"lon":-4.2161025,"name":"An Stuc","number":"M034","range":"Lawers Range"},{"Translation":"Little hill","gridref":"NN 457 741","height":1116.0,"lat":56.832675,"lon":-4.5305432,"name":"Aonach Beag","number":"M037","range":"Ben Alder Forest"},{"Translation":"Little hill","gridref":"NN 196 715","height":1234.0,"lat":56.799952,"lon":-4.955875,"name":"Aonach Beag","number":"M007","range":"Nevis Range"},{"Translation":null,"gridref":"NH 057 324","height":899.0,"lat":57.34057533,"lon":-5.2331157335,"name":"Aonach Buidhe","number":"C184","range":"None"},{"Translation":"Middle hill","gridref":"NH 049 137","height":1001.0,"lat":57.172519,"lon":-5.2288254,"name":"Aonach Mheadhoin","number":"M135","range":"Glen Shiel; Brothers Ridge"},{"Translation":"Big hill","gridref":"NN 192 729","height":1221.0,"lat":56.812357,"lon":-4.9634073,"name":"Aonach Mor","number":"M008","range":"Nevis Range"},{"Translation":null,"gridref":"NH 173 180","height":888.0,"lat":57.2162007118,"lon":-5.0295416092,"name":"Aonach Shasuinn","number":"C173","range":"None"},{"Translation":"Trembling hill","gridref":"NH 050 083","height":1021.0,"lat":57.12413,"lon":-5.2229561,"name":"Aonach air Chrith","number":"M109","range":"South Glen Shiel; Glen Shiel"},{"Translation":null,"gridref":"NC 302 461","height":787.0,"lat":58.3703363871,"lon":-4.9069446462,"name":"Arkle","number":"C219","range":"None"},{"Translation":null,"gridref":"NM 393 952","height":812.0,"lat":56.974247717,"lon":-6.2983158715,"name":"Askival","number":"C234","range":"None"},{"Translation":null,"gridref":"NN 808 308","height":789.0,"lat":56.4542400492,"lon":-3.9362765541,"name":"Auchnafree Hill","number":"C012","range":"None"},{"Translation":null,"gridref":"NH 222 489","height":849.0,"lat":57.4953247806,"lon":-4.970707622,"name":"Bac an Eich","number":"C180","range":"None"},{"Translation":null,"gridref":"NG 870 654","height":875.0,"lat":57.6280769537,"lon":-5.5729826708,"name":"Baosbheinn","number":"C191","range":"None"},{"Translation":"From Celtic meaning the field of hard water","gridref":"NN 344 432","height":1038.0,"lat":56.5515,"lon":-4.6956162,"name":"Beinn Achaladair","number":"M094","range":"Bridge of Orchy"},{"Translation":null,"gridref":"NG 930 761","height":792.0,"lat":57.7268044469,"lon":-5.4816071864,"name":"Beinn Airigh Charr","number":"C207","range":"None"},{"Translation":null,"gridref":"NN 140 857","height":796.0,"lat":56.9251344783,"lon":-5.0602181531,"name":"Beinn Bhan","number":"C167","range":"None"},{"Translation":null,"gridref":"NG 803 450","height":896.0,"lat":57.4419973411,"lon":-5.6668295288,"name":"Beinn Bhan","number":"C195","range":"None"},{"Translation":"Hill of the mouth","gridref":"NN 516 717","height":1019.0,"lat":56.813056,"lon":-4.4325478,"name":"Beinn Bheoil","number":"M112","range":"Ben Alder Forest"},{"Translation":null,"gridref":"NS 154 983","height":779.0,"lat":56.1415812671,"lon":-4.9749103927,"name":"Beinn Bheula","number":"C031","range":"None"},{"Translation":null,"gridref":"NN 868 820","height":912.44,"lat":56.915444115,"lon":-3.8614644193,"name":"Beinn Bhreac","number":"C076","range":"None"},{"Translation":"Speckled hill","gridref":"NO 058 971","height":931.0,"lat":57.055294,"lon":-3.5546379,"name":"Beinn Bhreac","number":"M249","range":"Cairngorms"},{"Translation":null,"gridref":"NN 302 339","height":802.0,"lat":56.4665504793,"lon":-4.7595298051,"name":"Beinn Bhreac-liath","number":"C058","range":"Glen Orchy"},{"Translation":"Hill of the mastiff","gridref":"NN 954 922","height":1157.0,"lat":57.009051,"lon":-3.7239721,"name":"Beinn Bhrotain","number":"M019","range":"Cairngorms"},{"Translation":null,"gridref":"NM 821 967","height":855.0,"lat":57.0098528252,"lon":-5.5942691421,"name":"Beinn Bhuidhe","number":"C153","range":"None"},{"Translation":"Yellow hill","gridref":"NN 203 187","height":948.0,"lat":56.326494,"lon":-4.9078278,"name":"Beinn Bhuidhe","number":"M216","range":"Loch Fyne"},{"Translation":"Possibly hill of the hawk","gridref":"NN 367 179","height":933.0,"lat":56.325253,"lon":-4.6424337,"name":"Beinn Chabhair","number":"M244","range":"Loch Lomond; Crianlarich"},{"Translation":null,"gridref":"NN 358 328","height":818.0,"lat":56.4586635619,"lon":-4.6678834088,"name":"Beinn Chaorach","number":"C043","range":"None"},{"Translation":null,"gridref":"NN 280 292","height":880.0,"lat":56.4235778245,"lon":-4.7921592513,"name":"Beinn Chuirn","number":"C023","range":"None"},{"Translation":null,"gridref":"NG 892 502","height":903.0,"lat":57.4928366062,"lon":-5.5228637453,"name":"Beinn Damh","number":"C194","range":"None"},{"Translation":"Red hill","gridref":"NN 852 777","height":1008.0,"lat":56.876439,"lon":-3.8852428,"name":"Beinn Dearg","number":"M124","range":"None"},{"Translation":"Red hill","gridref":"NH 259 811","height":1084.0,"lat":57.785613,"lon":-4.9300499,"name":"Beinn Dearg","number":"M057","range":"None"},{"Translation":null,"gridref":"NN 608 497","height":830.0,"lat":56.6184206807,"lon":-4.2710246341,"name":"Beinn Dearg","number":"C035","range":"None"},{"Translation":null,"gridref":"NG 895 608","height":913.7,"lat":57.5880102864,"lon":-5.5270563602,"name":"Beinn Dearg","number":"C188","range":"None"},{"Translation":null,"gridref":"NH 019 811","height":820.0,"lat":57.7756522963,"lon":-5.3361370214,"name":"Beinn Dearg Bheag","number":"C205","range":"None"},{"Translation":null,"gridref":"NH 032 799","height":906.28,"lat":57.7654642365,"lon":-5.3132675806,"name":"Beinn Dearg Mor","number":"C202","range":"None"},{"Translation":"Gaelic dobhran, hill of the streamlet","gridref":"NN 325 378","height":1076.0,"lat":56.502368,"lon":-4.7230054,"name":"Beinn Dorain","number":"M064","range":"Bridge of Orchy"},{"Translation":null,"gridref":"NH 037 381","height":797.0,"lat":57.3908367675,"lon":-5.2709370358,"name":"Beinn Dronaig","number":"C183","range":"None"},{"Translation":"Black-rock hill","gridref":"NN 307 254","height":978.0,"lat":56.390451,"lon":-4.7441747,"name":"Beinn Dubhchraig","number":"M175","range":"Tyndrum"},{"Translation":null,"gridref":"NN 601 158","height":813.0,"lat":56.3138942985,"lon":-4.2642235787,"name":"Beinn Each","number":"C013","range":"None"},{"Translation":"Delightful hill","gridref":"NN 449 733","height":1102.0,"lat":56.825229,"lon":-4.5431533,"name":"Beinn Eibhinn","number":"M048","range":"Ben Alder Forest"},{"Translation":"File hill (big red peak)","gridref":"NG 951 611","height":1010.0,"lat":57.593272,"lon":-5.4301154,"name":"Beinn Eighe (Ruadh-stac Mor)","number":"M120","range":"None"},{"Translation":null,"gridref":"NH 225 805","height":890.0,"lat":57.7789003936,"lon":-4.988962895,"name":"Beinn Enaiglair","number":"C210","range":"None"},{"Translation":"Fowling hill","gridref":"NN 135 328","height":989.0,"lat":56.450366,"lon":-5.0276621,"name":"Beinn Eunaich","number":"M156","range":"Loch Awe"},{"Translation":"Long hill","gridref":"NH 018 192","height":1032.0,"lat":57.220516,"lon":-5.2843886,"name":"Beinn Fhada","number":"M100","range":"None"},{"Translation":"Finlay's hill","gridref":"NH 115 282","height":1005.0,"lat":57.305336,"lon":-5.1308563,"name":"Beinn Fhionnlaidh","number":"M128","range":"None"},{"Translation":"Finlay's hill","gridref":"NN 095 497","height":959.0,"lat":56.600373,"lon":-5.1048453,"name":"Beinn Fhionnlaidh","number":"M198","range":"None"},{"Translation":"Greenish-grey hill","gridref":"NN 625 404","height":1103.0,"lat":56.535434,"lon":-4.2374315,"name":"Beinn Ghlas","number":"M047","range":"Lawers Range"},{"Translation":"Perhaps sheltering or peaceful hill","gridref":"NN 413 383","height":1078.0,"lat":56.509906,"lon":-4.5805037,"name":"Beinn Heasgarnich","number":"M062","range":"Loch Lochay"},{"Translation":null,"gridref":"NN 296 900","height":805.0,"lat":56.9697194238,"lon":-4.8066071896,"name":"Beinn Iaruinn","number":"C120","range":"None"},{"Translation":"Butter hill","gridref":"NN 255 084","height":1011.0,"lat":56.236013,"lon":-4.8170373,"name":"Beinn Ime","number":"M118","range":"Loch Lomond; Arrochar Alps"},{"Translation":"Big hill of the edge-point","gridref":"NO 045 792","height":1045.0,"lat":56.894286,"lon":-3.5692843,"name":"Beinn Iutharn Mhor","number":"M088","range":"None"},{"Translation":null,"gridref":"NG 981 732","height":859.0,"lat":57.7031228379,"lon":-5.3934317166,"name":"Beinn Lair","number":"C203","range":"None"},{"Translation":null,"gridref":"NC 320 294","height":792.0,"lat":58.2212295161,"lon":-4.8639907577,"name":"Beinn Leoid","number":"C225","range":"None"},{"Translation":"Big grey hill","gridref":"NG 964 519","height":926.0,"lat":57.511368,"lon":-5.4007028,"name":"Beinn Liath Mhor","number":"M258","range":"None"},{"Translation":"Big grey hill of Fannich","gridref":"NH 219 724","height":954.0,"lat":57.706003,"lon":-4.9907703,"name":"Beinn Liath Mhor Fannaich","number":"M209","range":"Loch Fannich"},{"Translation":null,"gridref":"NH 280 713","height":766.0,"lat":57.6985139926,"lon":-4.8897955141,"name":"Beinn Liath Mhor a'Ghiubhais Li [Beinn Liath Mhor a'Ghiuthais]","number":"C209","range":"None"},{"Translation":null,"gridref":"NN 242 079","height":858.0,"lat":56.2310503168,"lon":-4.839547625,"name":"Beinn Luibhean","number":"C024","range":"None"},{"Translation":null,"gridref":"NN 134 525","height":907.0,"lat":56.6270637222,"lon":-5.0457918853,"name":"Beinn Maol Chaluim","number":"C049","range":"None"},{"Translation":"Monk hill","gridref":"NN 373 411","height":953.0,"lat":56.533668,"lon":-4.6471796,"name":"Beinn Mhanach","number":"M211","range":"Bridge of Orchy"},{"Translation":"Middle hill","gridref":"NJ 024 016","height":1182.0,"lat":57.094994,"lon":-3.6124189,"name":"Beinn Mheadhoin","number":"M013","range":"Cairngorms"},{"Translation":null,"gridref":"NN 880 759","height":900.8,"lat":56.8609655458,"lon":-3.8390538343,"name":"Beinn Mheadhonach","number":"C077","range":"None"},{"Translation":null,"gridref":"NM 828 788","height":783.0,"lat":56.8496936083,"lon":-5.5673185061,"name":"Beinn Mhic Cedidh","number":"C126","range":"None"},{"Translation":null,"gridref":"NN 221 502","height":864.0,"lat":56.6098128001,"lon":-4.9022794452,"name":"Beinn Mhic Chasgaig","number":"C056","range":"None"},{"Translation":null,"gridref":"NN 208 350","height":796.0,"lat":56.4729394429,"lon":-4.9129569935,"name":"Beinn Mhic-Mhonaidh","number":"C059","range":"Glen Orchy"},{"Translation":null,"gridref":"NN 587 654","height":841.7,"lat":56.7587210464,"lon":-4.3139025996,"name":"Beinn Mholach","number":"C070","range":"None"},{"Translation":"Notched Mountain","gridref":"NN 271 066","height":926.0,"lat":56.220445,"lon":-4.790082,"name":"Beinn Narnain","number":"M259","range":"Loch Lomond; Arrochar Alps"},{"Translation":null,"gridref":"NN 337 338","height":901.0,"lat":56.4669013356,"lon":-4.7026205684,"name":"Beinn Odhar","number":"C039","range":"None"},{"Translation":null,"gridref":"NM 846 778","height":882.0,"lat":56.8415653266,"lon":-5.5369214713,"name":"Beinn Odhar Bheag","number":"C121","range":"None"},{"Translation":null,"gridref":"NN 448 642","height":868.0,"lat":56.743529383,"lon":-4.5406310746,"name":"Beinn Pharlagain [Ben Pharlagain - Meall na Meoig]","number":"C067","range":"Loch Ossian"},{"Translation":null,"gridref":"NM 766 654","height":845.0,"lat":56.7266200866,"lon":-5.6573368799,"name":"Beinn Resipol","number":"C131","range":"None"},{"Translation":"Probably scree or gravel hill","gridref":"NG 835 126","height":974.0,"lat":57.153061,"lon":-5.5811045,"name":"Beinn Sgritheall","number":"M183","range":"None"},{"Translation":"Unknown","gridref":"NN 053 460","height":937.0,"lat":56.565459,"lon":-5.1703638,"name":"Beinn Sgulaird","number":"M237","range":"Benderloch"},{"Translation":null,"gridref":"NC 361 572","height":773.0,"lat":58.4721548933,"lon":-4.8139507309,"name":"Beinn Spionnaidh","number":"C221","range":"None"},{"Translation":null,"gridref":"NN 474 163","height":771.0,"lat":56.3144627683,"lon":-4.4699062336,"name":"Beinn Stacach [Ceann na Baintighearna] [Stob Fear-tomhais] [Beinn Stacath]","number":"C020","range":"None"},{"Translation":null,"gridref":"NM 625 347","height":761.7,"lat":56.4444854008,"lon":-5.8597779012,"name":"Beinn Talaidh","number":"C237","range":"None"},{"Translation":null,"gridref":"NR 960 412","height":826.0,"lat":55.6214783094,"lon":-5.2442242292,"name":"Beinn Tarsuinn","number":"C241","range":"None"},{"Translation":"Transverse hill","gridref":"NH 039 728","height":937.0,"lat":57.7021,"lon":-5.2926514,"name":"Beinn Tarsuinn","number":"M238","range":"Fisherfield Forest"},{"Translation":"Forge hill","gridref":"NN 361 859","height":915.0,"lat":56.935276,"lon":-4.6953094,"name":"Beinn Teallach","number":"M282","range":"None"},{"Translation":null,"gridref":"NN 361 859","height":914.6,"lat":56.9352789078,"lon":-4.6969497922,"name":"Beinn Teallach","number":"C112","range":"None"},{"Translation":null,"gridref":"NH 055 433","height":863.0,"lat":57.4382446356,"lon":-5.2450960178,"name":"Beinn Tharsuinn","number":"C177","range":"None"},{"Translation":null,"gridref":"NN 086 439","height":840.0,"lat":56.5479807191,"lon":-5.1177181052,"name":"Beinn Trilleachan","number":"C051","range":"None"},{"Translation":"Hill of the hillocks","gridref":"NN 416 196","height":946.0,"lat":56.342175,"lon":-4.564307,"name":"Beinn Tulaichean","number":"M220","range":"Crianlarich; Loch Lomond"},{"Translation":null,"gridref":"NN 280 331","height":840.0,"lat":56.4585739433,"lon":-4.7947325203,"name":"Beinn Udlaidh","number":"C057","range":"None"},{"Translation":"Gloomy mountain","gridref":"NN 579 739","height":1011.0,"lat":56.834771,"lon":-4.3306736,"name":"Beinn Udlamain","number":"M119","range":"None"},{"Translation":"Table-hill","gridref":"NJ 092 006","height":1197.0,"lat":57.087407,"lon":-3.4998747,"name":"Beinn a' Bhuird","number":"M011","range":"Cairngorms"},{"Translation":"Hill of the rowan","gridref":"NN 386 851","height":1052.0,"lat":56.928975,"lon":-4.6537624,"name":"Beinn a' Chaorainn","number":"M079","range":"None"},{"Translation":"Hill of the rowan","gridref":"NJ 045 013","height":1083.0,"lat":57.092741,"lon":-3.5776613,"name":"Beinn a' Chaorainn","number":"M058","range":"Cairngorms"},{"Translation":"Stonemason's hill","gridref":"NN 471 781","height":1087.0,"lat":56.869037,"lon":-4.5100265,"name":"Beinn a' Chlachair","number":"M056","range":"Ardverikie Forest"},{"Translation":"Hill of the creel or chest","gridref":"NN 250 256","height":916.0,"lat":56.390169,"lon":-4.8365197,"name":"Beinn a' Chleibh","number":"M279","range":"Tyndrum"},{"Translation":"Hill of the hood or shell","gridref":"NN 109 328","height":980.0,"lat":56.449331,"lon":-5.0697805,"name":"Beinn a' Chochuill","number":"M172","range":"Loch Awe"},{"Translation":"Hill of the rock, or hill of the clamshell","gridref":"NN 373 440","height":1081.0,"lat":56.559693,"lon":-4.6489979,"name":"Beinn a' Chreachain","number":"M061","range":"Bridge of Orchy"},{"Translation":"Hill of harm or danger","gridref":"NN 387 185","height":942.0,"lat":56.331323,"lon":-4.6104962,"name":"Beinn a' Chroin","number":"M231","range":"Loch Lomond; Crianlarich"},{"Translation":null,"gridref":"NH 360 434","height":862.0,"lat":57.4511821589,"lon":-4.7365723624,"name":"Beinn a'Bha'ach Ard [Beinn a'Bhathaich Ard]","number":"C178","range":"None"},{"Translation":null,"gridref":"NN 094 283","height":897.0,"lat":56.4083606427,"lon":-5.0932561733,"name":"Beinn a'Bhuiridh","number":"C054","range":"None"},{"Translation":null,"gridref":"NG 982 785","height":856.0,"lat":57.7506898711,"lon":-5.396217168,"name":"Beinn a'Chaisgein Mor","number":"C204","range":"None"},{"Translation":null,"gridref":"NN 347 364","height":886.0,"lat":56.4905858792,"lon":-4.6880318856,"name":"Beinn a'Chaisteil","number":"C040","range":"None"},{"Translation":null,"gridref":"NH 369 801","height":787.0,"lat":57.78078315,"lon":-4.7463497233,"name":"Beinn a'Chaisteil","number":"C213","range":"None"},{"Translation":null,"gridref":"NH 061 775","height":913.96,"lat":57.7452050497,"lon":-5.2625249888,"name":"Beinn a'Chlaidheimh","number":"C201","range":"None"},{"Translation":null,"gridref":"NN 354 130","height":768.7,"lat":56.2808308791,"lon":-4.6619349337,"name":"Beinn a'Choin","number":"C021","range":"None"},{"Translation":null,"gridref":"NN 246 566","height":857.0,"lat":56.6681792708,"lon":-4.8658806103,"name":"Beinn a'Chrulaiste","number":"C048","range":"None"},{"Translation":null,"gridref":"NN 684 617","height":892.0,"lat":56.7283461159,"lon":-4.15326886,"name":"Beinn a'Chuallaich","number":"C068","range":"None"},{"Translation":null,"gridref":"NN 462 710","height":901.9,"lat":56.8050223738,"lon":-4.5218261654,"name":"Beinn a'Chumhainn","number":"C066","range":"None"},{"Translation":"Hill of the scorching or singeing","gridref":"NN 331 408","height":1004.0,"lat":56.529503,"lon":-4.7151951,"name":"Beinn an Dothaidh","number":"M129","range":"Bridge of Orchy"},{"Translation":null,"gridref":"NG 905 646","height":855.0,"lat":57.6225441606,"lon":-5.5136074103,"name":"Beinn an Eoin","number":"C192","range":"None"},{"Translation":null,"gridref":"NN 218 078","height":901.7,"lat":56.2292595231,"lon":-4.8782217457,"name":"Beinn an Lochain","number":"C027","range":"None"},{"Translation":null,"gridref":"NR 498 749","height":785.0,"lat":55.9019845204,"lon":-6.0095427081,"name":"Beinn an Oir","number":"C238","range":"None"},{"Translation":null,"gridref":"NM 929 835","height":810.0,"lat":56.8964539489,"lon":-5.4053643148,"name":"Beinn an Tuim","number":"C163","range":"None"},{"Translation":null,"gridref":"NG 795 066","height":785.0,"lat":57.0973724886,"lon":-5.6458566795,"name":"Beinn na Caillich","number":"C156","range":"None"},{"Translation":"Mottled hill","gridref":"NN 376 695","height":935.0,"lat":56.788636,"lon":-4.6602128,"name":"Beinn na Lap","number":"M241","range":"Loch Ossian"},{"Translation":null,"gridref":"NG 854 120","height":805.0,"lat":57.1485770112,"lon":-5.553004904,"name":"Beinn na h-Eaglaise","number":"C142","range":"None"},{"Translation":null,"gridref":"NM 917 664","height":762.4,"lat":56.7425718551,"lon":-5.4110718125,"name":"Beinn na h-Uamha","number":"C136","range":"None"},{"Translation":null,"gridref":"NN 361 381","height":806.0,"lat":56.5063315726,"lon":-4.666352898,"name":"Beinn nam Fuaran","number":"C044","range":"None"},{"Translation":"Hill of the hinds","gridref":"NN 148 405","height":960.0,"lat":56.51996,"lon":-5.0120749,"name":"Beinn nan Aighenan","number":"M196","range":"Loch Etive"},{"Translation":null,"gridref":"NG 871 121","height":774.0,"lat":57.1502647397,"lon":-5.5249594132,"name":"Beinn nan Caorach","number":"C145","range":"None"},{"Translation":null,"gridref":"NN 419 309","height":849.0,"lat":56.4436967889,"lon":-4.5676824958,"name":"Beinn nan Imirean","number":"C042","range":"Loch Lochay; Crianlarich"},{"Translation":null,"gridref":"NN 541 412","height":909.6,"lat":56.5400849992,"lon":-4.3754557925,"name":"Beinn nan Oighreag","number":"C038","range":"None"},{"Translation":null,"gridref":"NM 899 986","height":887.0,"lat":57.0305048702,"lon":-5.4672659873,"name":"Ben Aden [Beinn an Aodainn]","number":"C150","range":"None"},{"Translation":"From the Alder Burn, meaning rock water","gridref":"NN 496 718","height":1148.0,"lat":56.813311,"lon":-4.4653344,"name":"Ben Alder","number":"M025","range":"Ben Alder Forest"},{"Translation":"Bed of the yellow stag","gridref":"NJ 131 018","height":1171.0,"lat":57.098936,"lon":-3.435963,"name":"Ben Avon, Leabaoidh an Daimh Bhuide","number":"M017","range":"Cairngorms; Ben Avon"},{"Translation":"Malcolm's hill","gridref":"NN 386 322","height":1025.0,"lat":56.454243,"lon":-4.6205492,"name":"Ben Challum","number":"M106","range":"Loch Lochay; Crianlarich"},{"Translation":"Probably mossy hill","gridref":"NN 773 308","height":931.0,"lat":56.453339,"lon":-3.9924244,"name":"Ben Chonzie (Ben-y-Hone)","number":"M250","range":"None"},{"Translation":"Stacky hill","gridref":"NN 069 304","height":1126.0,"lat":56.42618,"lon":-5.1327995,"name":"Ben Cruachan","number":"M031","range":"Loch Awe"},{"Translation":null,"gridref":"NN 218 043","height":847.0,"lat":56.1978538536,"lon":-4.87586347,"name":"Ben Donich","number":"C028","range":"None"},{"Translation":null,"gridref":"NO 100 722","height":806.0,"lat":56.8325275389,"lon":-3.4768242518,"name":"Ben Gulabin","number":"C085","range":"None"},{"Translation":null,"gridref":"NC 426 339","height":873.0,"lat":58.2655159149,"lon":-4.6864578126,"name":"Ben Hee","number":"C216","range":"None"},{"Translation":"Hill of the bay","gridref":"NC 477 501","height":927.0,"lat":58.412655,"lon":-4.6086743,"name":"Ben Hope","number":"M256","range":"Far North"},{"Translation":"Hill of the speckled cliff","gridref":"NC 585 299","height":962.0,"lat":58.235022,"lon":-4.4116218,"name":"Ben Klibreck","number":"M194","range":"Far North"},{"Translation":"Gaelic labhar, meaning loud (from a stream)","gridref":"NN 635 414","height":1214.0,"lat":56.544702,"lon":-4.2217107,"name":"Ben Lawers","number":"M010","range":"Lawers Range; Loch Tay"},{"Translation":null,"gridref":"NN 562 097","height":879.0,"lat":56.2579679339,"lon":-4.3239670808,"name":"Ben Ledi","number":"C015","range":"None"},{"Translation":"Beacon hill","gridref":"NN 367 028","height":974.0,"lat":56.189734,"lon":-4.6331056,"name":"Ben Lomond","number":"M184","range":"Loch Lomond"},{"Translation":null,"gridref":"NC 578 488","height":764.2,"lat":58.4043943055,"lon":-4.4364021914,"name":"Ben Loyal - An Caisteal","number":"C222","range":"None"},{"Translation":"Calf hill","gridref":"NN 266 263","height":1130.0,"lat":56.39704,"lon":-4.8110989,"name":"Ben Lui (Beinn Laoigh)","number":"M028","range":"Tyndrum"},{"Translation":"Hill of the son of Duff","gridref":"NN 989 989","height":1309.0,"lat":57.069993,"lon":-3.6690657,"name":"Ben Macdui","number":"M002","range":"Cairngorms"},{"Translation":"Big hill","gridref":"NM 525 330","height":966.0,"lat":56.424108,"lon":-6.0152005,"name":"Ben More","number":"M189","range":"Isle of Mull"},{"Translation":"Big hill","gridref":"NN 432 244","height":1174.0,"lat":56.385789,"lon":-4.5413166,"name":"Ben More (Glen Dochart)","number":"M016","range":"Loch Lomond; Crianlarich"},{"Translation":"Big hill of Assynt (Norse: ass, a rocky ridge)","gridref":"NC 318 201","height":998.0,"lat":58.137726,"lon":-4.8586846,"name":"Ben More Assynt","number":"M141","range":"Far North"},{"Translation":"Possibly from an old Gaelic word meaning venomous","gridref":"NN 166 712","height":1344.0,"lat":56.796088,"lon":-5.004712,"name":"Ben Nevis","number":"M001","range":"Nevis Range"},{"Translation":"Loch-outlet hill","gridref":"NN 287 253","height":1029.0,"lat":56.388832,"lon":-4.7764656,"name":"Ben Oss","number":"M101","range":"Tyndrum"},{"Translation":null,"gridref":"NJ 254 354","height":841.0,"lat":57.4028543645,"lon":-3.2432860108,"name":"Ben Rinnes","number":"C103","range":"None"},{"Translation":"Unknown","gridref":"NN 125 427","height":1078.0,"lat":56.538785,"lon":-5.05099,"name":"Ben Starav","number":"M063","range":"Loch Etive"},{"Translation":null,"gridref":"NN 240 972","height":904.0,"lat":57.0322180025,"lon":-4.903825934,"name":"Ben Tee","number":"C157","range":"None"},{"Translation":null,"gridref":"NO 373 746","height":896.0,"lat":56.8585742162,"lon":-3.0299411166,"name":"Ben Tirran","number":"C090","range":"None"},{"Translation":"Middle hill","gridref":"NN 277 098","height":916.0,"lat":56.249379,"lon":-4.7825008,"name":"Ben Vane","number":"M280","range":"Loch Lomond; Arrochar Alps"},{"Translation":"Hill of the bay","gridref":"NN 295 124","height":943.0,"lat":56.27336,"lon":-4.7551643,"name":"Ben Vorlich","number":"M229","range":"Loch Lomond; Arrochar Alps"},{"Translation":"Hill of the bay","gridref":"NN 629 189","height":985.0,"lat":56.34254,"lon":-4.2196495,"name":"Ben Vorlich (by Loch Earn)","number":"M165","range":"Loch Earn"},{"Translation":null,"gridref":"NN 950 632","height":842.0,"lat":56.7485634706,"lon":-3.7189837256,"name":"Ben Vrackie","number":"C084","range":"None"},{"Translation":null,"gridref":"NN 997 700","height":903.0,"lat":56.8106618604,"lon":-3.6447840839,"name":"Ben Vuirich","number":"C081","range":"None"},{"Translation":"Gaelic fuathas, meaning awesome hill","gridref":"NH 463 683","height":1046.0,"lat":57.67822,"lon":-4.5791532,"name":"Ben Wyvis, Glas Leathad Mor","number":"M085","range":"None"},{"Translation":null,"gridref":"NN 535 137","height":821.0,"lat":56.2930490127,"lon":-4.3697939586,"name":"Benvane","number":"C018","range":"None"},{"Translation":"Peak of the corrie of the barren or milkless cattle","gridref":"NH 049 412","height":945.0,"lat":57.419151,"lon":-5.2505263,"name":"Bidean a' Choire Sheasgaich","number":"M224","range":"None"},{"Translation":"Peak of the greenish-grey hollow","gridref":"NH 068 843","height":1062.0,"lat":57.806484,"lon":-5.2533352,"name":"Bidean a' Ghlas Thuill (An Teallach)","number":"M072","range":"None"},{"Translation":"Peak of the mountains","gridref":"NN 143 542","height":1150.0,"lat":56.642669,"lon":-5.0300142,"name":"Bidean nam Bian","number":"M023","range":"Glen Coe"},{"Translation":null,"gridref":"NM 889 930","height":867.0,"lat":56.9798351317,"lon":-5.479052334,"name":"Bidein a'Chabair","number":"C164","range":"None"},{"Translation":"Small peak","gridref":"NN 221 677","height":943.0,"lat":56.766821,"lon":-4.9123501,"name":"Binnean Beag","number":"M230","range":"Mamores"},{"Translation":"Big peak","gridref":"NN 212 663","height":1130.0,"lat":56.753916,"lon":-4.9260759,"name":"Binnein Mor","number":"M027","range":"Mamores"},{"Translation":"Blue hill, or possibly warm hill","gridref":"NG 529 217","height":928.0,"lat":57.219159,"lon":-6.0946748,"name":"Bla Bheinn (Blaven)","number":"M252","range":"Black Cuilin"},{"Translation":"Brindled greyish upper part","gridref":"NN 953 999","height":1296.0,"lat":57.078168,"lon":-3.7288277,"name":"Braeriach","number":"M003","range":"Cairngorms; Braeriach"},{"Translation":"Upland of the corrie of the round blisters","gridref":"NN 945 724","height":1070.0,"lat":56.831058,"lon":-3.7305333,"name":"Braigh Coire Chruinn-bhalgain","number":"M066","range":"None"},{"Translation":null,"gridref":"NM 975 866","height":765.0,"lat":56.926286986,"lon":-5.3322510679,"name":"Braigh nan Uamhachan","number":"C169","range":"None"},{"Translation":null,"gridref":"NC 286 157","height":815.0,"lat":58.097032074,"lon":-4.9118335666,"name":"Breabag","number":"C223","range":"None"},{"Translation":"Broad cairn","gridref":"NO 240 815","height":998.0,"lat":56.918553,"lon":-3.2499735,"name":"Broad Cairn","number":"M142","range":"White Mounth"},{"Translation":null,"gridref":"NT 146 235","height":840.0,"lat":55.4977965059,"lon":-3.3535824119,"name":"Broad Law","number":"C006","range":"None"},{"Translation":null,"gridref":"NJ 221 044","height":829.0,"lat":57.1239033563,"lon":-3.2884478475,"name":"Brown Cow Hill","number":"C098","range":"None"},{"Translation":"Slope of the deer forest","gridref":"NG 461 252","height":958.0,"lat":57.246797,"lon":-6.2105489,"name":"Bruach na Frithe","number":"M200","range":"Black Cuilin"},{"Translation":"Ferny corrie peak","gridref":"NN 191 548","height":925.0,"lat":56.649932,"lon":-4.9522757,"name":"Buachaille Etive Beag, Stob Coire Raineach","number":"M263","range":"Glen Coe"},{"Translation":"Small herdsman of Etive, black peak","gridref":"NN 179 535","height":958.0,"lat":56.637803,"lon":-4.9709013,"name":"Buachaille Etive Beag, Stob Dubh","number":"M201","range":"Glen Coe"},{"Translation":"Big herdsman of Etive, red peak","gridref":"NN 222 542","height":1021.0,"lat":56.645736,"lon":-4.9013718,"name":"Buachaille Etive Mor, Stob Dearg","number":"M110","range":"Glen Coe"},{"Translation":"Peak of the shoe","gridref":"NN 190 525","height":956.0,"lat":56.629258,"lon":-4.9522906,"name":"Buachaille Etive Mor, Stob na Broige","number":"M207","range":"Glen Coe"},{"Translation":null,"gridref":"NG 963 090","height":885.5,"lat":57.1266384136,"lon":-5.3701795833,"name":"Buidhe Bheinn","number":"C139","range":"None"},{"Translation":null,"gridref":"NG 956 087","height":879.0,"lat":57.1236374615,"lon":-5.3815085668,"name":"Buidhe Bheinn West Top","number":"C140","range":"None"},{"Translation":"Obscure","gridref":"NJ 041 063","height":1090.0,"lat":57.137555,"lon":-3.5861779,"name":"Bynack More","number":"M054","range":"Cairngorms"},{"Translation":"Hill of the point","gridref":"NO 222 825","height":1012.0,"lat":56.927235,"lon":-3.2798389,"name":"Cairn Bannoch","number":"M117","range":"White Mounth"},{"Translation":"Blue hill","gridref":"NJ 005 040","height":1244.0,"lat":57.116137,"lon":-3.6447166,"name":"Cairn Gorm","number":"M006","range":"Cairngorms"},{"Translation":"Hill of the barn","gridref":"NN 963 972","height":1291.0,"lat":57.05415,"lon":-3.7112231,"name":"Cairn Toul","number":"M004","range":"Cairngorms; Braeriach"},{"Translation":"Hill of the green grassy place","gridref":"NO 185 788","height":1064.0,"lat":56.893368,"lon":-3.3394189,"name":"Cairn of Claise","number":"M071","range":"None"},{"Translation":null,"gridref":"NX 594 979","height":797.0,"lat":55.2551688852,"lon":-4.2145743995,"name":"Cairnsmore of Carsphairn","number":"C005","range":"None"},{"Translation":null,"gridref":"NR 969 443","height":859.0,"lat":55.6496648186,"lon":-5.2322155071,"name":"Caisteal Abhail","number":"C240","range":"None"},{"Translation":null,"gridref":"NN 375 346","height":884.0,"lat":56.4754067623,"lon":-4.6414036521,"name":"Cam Chreag","number":"C041","range":"Loch Lochay; Crianlarich"},{"Translation":null,"gridref":"NN 536 491","height":862.0,"lat":56.6108402742,"lon":-4.3880639089,"name":"Cam Chreag","number":"C033","range":"None"},{"Translation":null,"gridref":"NC 202 187","height":847.0,"lat":58.1206077164,"lon":-5.0567568881,"name":"Canisp","number":"C230","range":"None"},{"Translation":"Hill of age","gridref":"NO 134 792","height":915.0,"lat":56.896035,"lon":-3.4232419,"name":"Carn Aosda","number":"M281","range":"None"},{"Translation":null,"gridref":"NH 338 875","height":842.0,"lat":57.8460321934,"lon":-4.8036748071,"name":"Carn Ban","number":"C211","range":"None"},{"Translation":"Hill of peat-banks","gridref":"NO 051 832","height":946.0,"lat":56.930329,"lon":-3.560938,"name":"Carn Bhac","number":"M221","range":"None"},{"Translation":null,"gridref":"NH 483 833","height":839.0,"lat":57.8135012161,"lon":-4.5565487115,"name":"Carn Chuinneag","number":"C212","range":"None"},{"Translation":"Red hill","gridref":"NN 417 661","height":941.0,"lat":56.759535,"lon":-4.5910671,"name":"Carn Dearg","number":"M232","range":"Loch Ossian"},{"Translation":"Red hill","gridref":"NN 504 764","height":1034.0,"lat":56.854855,"lon":-4.454945,"name":"Carn Dearg","number":"M098","range":"Ben Alder Forest"},{"Translation":"Red hill","gridref":"NH 635 023","height":945.0,"lat":57.091379,"lon":-4.2543197,"name":"Carn Dearg","number":"M225","range":"None"},{"Translation":null,"gridref":"NN 349 966","height":817.0,"lat":57.0308649709,"lon":-4.7237002888,"name":"Carn Dearg","number":"C113","range":"None"},{"Translation":null,"gridref":"NN 357 948","height":768.0,"lat":57.0149989717,"lon":-4.7093330592,"name":"Carn Dearg","number":"C118","range":"None"},{"Translation":null,"gridref":"NN 345 887","height":834.0,"lat":56.9598344785,"lon":-4.7250971521,"name":"Carn Dearg","number":"C119","range":"None"},{"Translation":null,"gridref":"NN 823 911","height":857.0,"lat":56.9960234086,"lon":-3.9396405999,"name":"Carn Dearg Mor","number":"C079","range":"None"},{"Translation":null,"gridref":"NJ 227 117","height":792.0,"lat":57.189564261,"lon":-3.2808020799,"name":"Carn Ealasaid","number":"C101","range":"None"},{"Translation":null,"gridref":"NH 485 063","height":781.0,"lat":57.1225862626,"lon":-4.5053522733,"name":"Carn Easgann Bana","number":"C117","range":"None"},{"Translation":"File hill","gridref":"NH 123 262","height":1183.0,"lat":57.287727,"lon":-5.1160797,"name":"Carn Eighe","number":"M012","range":"Glen Affric"},{"Translation":"Hill of movement","gridref":"NH 145 125","height":957.0,"lat":57.165737,"lon":-5.0694029,"name":"Carn Ghluasaid","number":"M203","range":"None"},{"Translation":"Blue hill","gridref":"NN 635 500","height":1029.0,"lat":56.621905,"lon":-4.2262461,"name":"Carn Gorm","number":"M103","range":"Carn Mairg"},{"Translation":"Grey hill","gridref":"NN 936 698","height":975.0,"lat":56.807507,"lon":-3.7441891,"name":"Carn Liath","number":"M181","range":"None"},{"Translation":"Grey hill","gridref":"NN 472 903","height":1006.0,"lat":56.978561,"lon":-4.5157492,"name":"Carn Liath","number":"M126","range":"None"},{"Translation":null,"gridref":"NO 164 976","height":861.5,"lat":57.0618337975,"lon":-3.3803313834,"name":"Carn Liath","number":"C096","range":"None"},{"Translation":"Hill of sorrow","gridref":"NN 684 512","height":1041.0,"lat":56.634081,"lon":-4.1470639,"name":"Carn Mairg","number":"M091","range":"Carn Mairg"},{"Translation":null,"gridref":"NJ 265 183","height":804.0,"lat":57.2494635998,"lon":-3.2198756179,"name":"Carn Mor","number":"C104","range":"None"},{"Translation":null,"gridref":"NM 903 909","height":829.0,"lat":56.9616417367,"lon":-5.4542420191,"name":"Carn Mor","number":"C165","range":"None"},{"Translation":"Big red hill","gridref":"NN 177 721","height":1220.0,"lat":56.804595,"lon":-4.9873704,"name":"Carn Mor Dearg","number":"M009","range":"Nevis Range"},{"Translation":"Hill of the basket, or of the old man","gridref":"NH 683 058","height":920.0,"lat":57.124196,"lon":-4.177013,"name":"Carn Sgulain","number":"M271","range":"None"},{"Translation":"Hill of the kite or buzzard","gridref":"NN 915 758","height":963.0,"lat":56.860896,"lon":-3.7811202,"name":"Carn a' Chlamain","number":"M192","range":"None"},{"Translation":"Hill of the beautiful corrie","gridref":"NO 226 845","height":1110.0,"lat":56.945264,"lon":-3.2738813,"name":"Carn a' Choire Boidheach","number":"M042","range":"White Mounth"},{"Translation":"Hill of the goose","gridref":"NO 107 767","height":975.0,"lat":56.873072,"lon":-3.4666687,"name":"Carn a' Gheoidh","number":"M180","range":"None"},{"Translation":"Hill of the pass","gridref":"NN 994 951","height":1037.0,"lat":57.035981,"lon":-3.6593002,"name":"Carn a' Mhaim","number":"M095","range":"Cairngorms"},{"Translation":null,"gridref":"NH 136 188","height":865.0,"lat":57.2218859115,"lon":-5.0914607675,"name":"Carn a'Choire Ghairbh","number":"C174","range":"None"},{"Translation":null,"gridref":"NH 416 034","height":817.0,"lat":57.0942363943,"lon":-4.6175395485,"name":"Carn a'Chuilinn","number":"C114","range":"None"},{"Translation":"Hill of the fiddler","gridref":"NN 904 842","height":994.0,"lat":56.93606,"lon":-3.8027821,"name":"Carn an Fhidhleir","number":"M148","range":"None"},{"Translation":null,"gridref":"NH 725 071","height":878.0,"lat":57.13705426,"lon":-4.1091430597,"name":"Carn an Fhreiceadain","number":"C109","range":"None"},{"Translation":"Hill of the king","gridref":"NO 028 772","height":1029.0,"lat":56.875973,"lon":-3.596412,"name":"Carn an Righ","number":"M102","range":"None"},{"Translation":"Hill of the boar","gridref":"NO 174 804","height":1019.0,"lat":56.907543,"lon":-3.3579908,"name":"Carn an Tuirc","number":"M113","range":"None"},{"Translation":"Big hill of the priest","gridref":"NO 208 843","height":1047.0,"lat":56.943163,"lon":-3.3033973,"name":"Carn an t-Sagairt Mor","number":"M083","range":"White Mounth"},{"Translation":"Cairn of the curve","gridref":"NN 677 821","height":941.0,"lat":56.911276,"lon":-4.1744557,"name":"Carn na Caim","number":"M233","range":"None"},{"Translation":null,"gridref":"NO 127 938","height":818.0,"lat":57.0270217714,"lon":-3.44002772,"name":"Carn na Drochaide","number":"C100","range":"None"},{"Translation":null,"gridref":"NH 584 112","height":810.0,"lat":57.1697233426,"lon":-4.344532793,"name":"Carn na Laraiche Maoile","number":"C116","range":"None"},{"Translation":null,"gridref":"NM 886 698","height":786.0,"lat":56.7716656704,"lon":-5.4646258278,"name":"Carn na Nathrach","number":"C132","range":"None"},{"Translation":null,"gridref":"NH 598 144","height":811.0,"lat":57.1988752147,"lon":-4.3231742047,"name":"Carn na Saobhaidhe","number":"C115","range":"None"},{"Translation":"Hill of the goats","gridref":"NN 971 733","height":1121.0,"lat":56.839723,"lon":-3.6883101,"name":"Carn nan Gabhar","number":"M032","range":"None"},{"Translation":"Hill of the goats","gridref":"NH 181 343","height":992.0,"lat":57.362732,"lon":-5.025969,"name":"Carn nan Gobhar (Glen Cannich)","number":"M152","range":"Loch Mullardoch"},{"Translation":"Hill of the goats","gridref":"NH 273 439","height":992.0,"lat":57.452438,"lon":-4.8799889,"name":"Carn nan Gobhar (Glen Strathfarrar)","number":"M153","range":"Strathfarrar"},{"Translation":"Red hill","gridref":"NN 377 741","height":1046.0,"lat":56.82995,"lon":-4.6615039,"name":"Chno Dearg","number":"M086","range":"Loch Treig"},{"Translation":null,"gridref":"NR 972 431","height":799.0,"lat":55.6390249458,"lon":-5.2265557856,"name":"Cir Mhor","number":"C242","range":"None"},{"Translation":"Black chest","gridref":"NH 062 166","height":979.0,"lat":57.19908,"lon":-5.2096173,"name":"Ciste Dhubh","number":"M173","range":"None"},{"Translation":null,"gridref":"NN 233 007","height":763.5,"lat":56.1661091353,"lon":-4.8492700422,"name":"Cnoc Coinnich","number":"C030","range":"None"},{"Translation":"Hill of the dog, or hill of the meeting","gridref":"NH 274 816","height":978.0,"lat":57.790678,"lon":-4.9052176,"name":"Cona' Mheall","number":"M176","range":"None"},{"Translation":null,"gridref":"NO 279 865","height":865.0,"lat":56.9640869589,"lon":-3.1874959404,"name":"Conachcraig","number":"C087","range":"None"},{"Translation":"Hill of the dog, or hill of the meeting","gridref":"NC 303 199","height":987.0,"lat":58.135359,"lon":-4.8839811,"name":"Conival","number":"M158","range":"Far North"},{"Translation":null,"gridref":"NJ 302 278","height":755.0,"lat":57.3353629062,"lon":-3.1612360536,"name":"Cook's Cairn","number":"C106","range":"None"},{"Translation":null,"gridref":"NN 429 995","height":892.0,"lat":57.0596838878,"lon":-4.5936229728,"name":"Corrieyairack Hill","number":"C108","range":"None"},{"Translation":null,"gridref":"NJ 280 288","height":781.0,"lat":57.3440011776,"lon":-3.1980770207,"name":"Corryhabbie Hill","number":"C105","range":"None"},{"Translation":null,"gridref":"NX 497 870","height":814.0,"lat":55.1544444762,"lon":-4.3614367848,"name":"Corserine","number":"C003","range":"None"},{"Translation":null,"gridref":"NT 168 247","height":830.2,"lat":55.5089560356,"lon":-3.3191136735,"name":"Cramalt Craig","number":"C008","range":"None"},{"Translation":null,"gridref":"NC 350 556","height":801.0,"lat":58.4573880782,"lon":-4.8316671847,"name":"Cranstackie","number":"C218","range":"None"},{"Translation":null,"gridref":"NM 870 576","height":853.0,"lat":56.6615391813,"lon":-5.4806773519,"name":"Creach Bheinn","number":"C137","range":"None"},{"Translation":null,"gridref":"NN 023 422","height":810.0,"lat":56.5301236482,"lon":-5.2189820836,"name":"Creach Bheinn","number":"C052","range":"Benderloch"},{"Translation":"Slabby rock","gridref":"NO 154 745","height":987.0,"lat":56.854195,"lon":-3.3888548,"name":"Creag Leachach","number":"M159","range":"None"},{"Translation":null,"gridref":"NN 545 255","height":808.6,"lat":56.3992804494,"lon":-4.3601726529,"name":"Creag Mac Ranaich","number":"C019","range":"None"},{"Translation":"Bogland rock","gridref":"NN 418 875","height":1128.0,"lat":56.951617,"lon":-4.6027428,"name":"Creag Meagaidh","number":"M030","range":"None"},{"Translation":null,"gridref":"NJ 057 047","height":895.0,"lat":57.123522753,"lon":-3.5594659306,"name":"Creag Mhor","number":"C095","range":"None"},{"Translation":"Big rock","gridref":"NN 391 361","height":1047.0,"lat":56.489415,"lon":-4.6148522,"name":"Creag Mhor","number":"M084","range":"Loch Lochay; Crianlarich"},{"Translation":"Meaning uncertain, perhaps from the surname Petrie","gridref":"NN 487 814","height":924.0,"lat":56.899179,"lon":-4.4857724,"name":"Creag Pitridh","number":"M264","range":"Ardverikie Forest"},{"Translation":null,"gridref":"NH 096 751","height":807.0,"lat":57.7251797207,"lon":-5.2017593929,"name":"Creag Rainich","number":"C206","range":"None"},{"Translation":null,"gridref":"NN 708 323","height":879.0,"lat":56.465071687,"lon":-4.0993213099,"name":"Creag Uchdag","number":"C011","range":"None"},{"Translation":"Rock of the large rounded hill","gridref":"NH 087 077","height":947.0,"lat":57.120303,"lon":-5.1614814,"name":"Creag a' Mhaim","number":"M218","range":"South Glen Shiel; Glen Shiel"},{"Translation":null,"gridref":"NO 157 981","height":863.0,"lat":57.0661963736,"lon":-3.3920435872,"name":"Creag an Dail Bheag","number":"C097","range":"None"},{"Translation":"Rock of the stags","gridref":"NG 983 111","height":918.0,"lat":57.146349,"lon":-5.335688,"name":"Creag nan Damh","number":"M275","range":"South Glen Shiel; Glen Shiel"},{"Translation":null,"gridref":"NO 154 841","height":834.0,"lat":56.9404135557,"lon":-3.3922841944,"name":"Creag nan Gabhar","number":"C088","range":"None"},{"Translation":null,"gridref":"NN 744 368","height":888.0,"lat":56.5064474671,"lon":-4.0430452872,"name":"Creagan na Beinne","number":"C010","range":"None"},{"Translation":"Unknown","gridref":"NN 238 506","height":1100.0,"lat":56.614041,"lon":-4.8728572,"name":"Creise","number":"M050","range":"Loch Etive"},{"Translation":"Stack of the high part","gridref":"NN 409 212","height":1046.0,"lat":56.3563,"lon":-4.5765879,"name":"Cruach Ardrain","number":"M087","range":"Loch Lomond; Crianlarich"},{"Translation":null,"gridref":"NN 279 763","height":857.0,"lat":56.8461677714,"lon":-4.8252685187,"name":"Cruach Innse","number":"C061","range":"None"},{"Translation":null,"gridref":"NC 140 088","height":769.0,"lat":58.0292609219,"lon":-5.1542349233,"name":"Cul Beag","number":"C231","range":"None"},{"Translation":null,"gridref":"NC 162 119","height":849.0,"lat":58.0579793054,"lon":-5.119376889,"name":"Cul Mor","number":"C229","range":"None"},{"Translation":null,"gridref":"NO 193 988","height":900.0,"lat":57.0731282002,"lon":-3.3328926617,"name":"Culardoch","number":"C094","range":"None"},{"Translation":"Blue hill of Derry","gridref":"NO 017 980","height":1155.0,"lat":57.062518,"lon":-3.6225541,"name":"Derry Cairngorm","number":"M020","range":"Cairngorms"},{"Translation":"Gaelic dris, a thorn bush or bramble","gridref":"NO 271 735","height":947.0,"lat":56.8472,"lon":-3.1967678,"name":"Driesh","number":"M219","range":"None"},{"Translation":null,"gridref":"NM 791 791","height":869.0,"lat":56.8506387572,"lon":-5.6283171433,"name":"Druim Fiaclach","number":"C124","range":"None"},{"Translation":null,"gridref":"NM 881 683","height":803.0,"lat":56.7579879092,"lon":-5.4715697351,"name":"Druim Garbh","number":"C128","range":"None"},{"Translation":"Ridge of the fox","gridref":"NH 074 084","height":987.0,"lat":57.126039,"lon":-5.1834561,"name":"Druim Shionnach","number":"M160","range":"South Glen Shiel; Glen Shiel"},{"Translation":null,"gridref":"NM 874 727","height":770.0,"lat":56.7971238018,"lon":-5.4867024705,"name":"Druim Tarsuinn [Stob a'Bhealach an Sgriodain]","number":"C135","range":"None"},{"Translation":null,"gridref":"NH 130 076","height":789.0,"lat":57.1211788239,"lon":-5.0929794791,"name":"Druim nan Cnamh [Beinn Loinne]","number":"C143","range":"None"},{"Translation":null,"gridref":"NM 672 362","height":766.0,"lat":56.4602747446,"lon":-5.7847755709,"name":"Dun da Ghaoithe","number":"C236","range":"None"},{"Translation":"Web of the white stones","gridref":"NH 257 842","height":927.0,"lat":57.813343,"lon":-4.9356683,"name":"Eididh nan Clach Geala","number":"M257","range":"None"},{"Translation":null,"gridref":"NH 021 317","height":868.0,"lat":57.3327494014,"lon":-5.2924216911,"name":"Faochaig","number":"C186","range":"None"},{"Translation":null,"gridref":"NN 840 553","height":782.3,"lat":56.6750233108,"lon":-3.8953209013,"name":"Farragon Hill","number":"C037","range":"None"},{"Translation":"Pale-coloured hill","gridref":"NH 147 621","height":933.0,"lat":57.610712,"lon":-5.1035047,"name":"Fionn Bheinn","number":"M246","range":"Loch Fannich"},{"Translation":null,"gridref":"NC 315 506","height":911.05,"lat":58.411202624,"lon":-4.8880095762,"name":"Foinaven [Foinne Bhein] - Ganu Mor","number":"C215","range":"None"},{"Translation":null,"gridref":"NM 986 940","height":858.0,"lat":56.9931316102,"lon":-5.3200760715,"name":"Fraoch Bheinn","number":"C152","range":"None"},{"Translation":null,"gridref":"NN 029 517","height":879.0,"lat":56.6155880373,"lon":-5.2164664393,"name":"Fraochaidh","number":"C050","range":"None"},{"Translation":null,"gridref":"NM 853 563","height":766.0,"lat":56.6491052155,"lon":-5.5073559974,"name":"Fuar Bheinn","number":"C138","range":"None"},{"Translation":null,"gridref":"NG 975 489","height":907.0,"lat":57.4849637213,"lon":-5.3831464548,"name":"Fuar Tholl","number":"C193","range":"None"},{"Translation":null,"gridref":"NN 460 985","height":896.0,"lat":57.051756274,"lon":-4.5418633584,"name":"Gairbeinn","number":"C107","range":"None"},{"Translation":"Roaring","gridref":"NN 025 995","height":919.0,"lat":57.04414,"lon":-5.2572466,"name":"Gairich","number":"M272","range":"None"},{"Translation":null,"gridref":"NM 904 622","height":885.0,"lat":56.7043258222,"lon":-5.4289068343,"name":"Garbh Bheinn","number":"C129","range":"None"},{"Translation":null,"gridref":"NN 169 600","height":867.0,"lat":56.6957310586,"lon":-4.994040684,"name":"Garbh Bheinn","number":"C047","range":"None"},{"Translation":"Big rough place of the breast","gridref":"NM 909 961","height":1013.0,"lat":57.008539,"lon":-5.4452553,"name":"Garbh Chioch Mhor","number":"M116","range":"None"},{"Translation":null,"gridref":"NG 531 232","height":808.0,"lat":57.2327101466,"lon":-6.0986399895,"name":"Garbh-bheinn","number":"C232","range":"None"},{"Translation":"White hill","gridref":"NN 504 811","height":1049.0,"lat":56.897038,"lon":-4.457713,"name":"Geal Charn","number":"M081","range":"Ardverikie Forest"},{"Translation":null,"gridref":"NN 156 942","height":804.0,"lat":57.00202494,"lon":-5.0401300511,"name":"Geal Charn","number":"C160","range":"None"},{"Translation":"White hill","gridref":"NN 561 987","height":926.0,"lat":57.056813,"lon":-4.3742613,"name":"Geal Charn","number":"M260","range":"None"},{"Translation":null,"gridref":"NJ 090 126","height":821.0,"lat":57.1951295356,"lon":-3.5078372732,"name":"Geal Charn","number":"C099","range":"None"},{"Translation":"White hill","gridref":"NN 469 746","height":1132.0,"lat":56.837559,"lon":-4.5111977,"name":"Geal-Charn","number":"M026","range":"Ben Alder Forest"},{"Translation":"White hill","gridref":"NN 596 782","height":917.0,"lat":56.873886,"lon":-4.3052094,"name":"Geal-charn","number":"M278","range":"None"},{"Translation":null,"gridref":"NH 836 123","height":824.0,"lat":57.1866872258,"lon":-3.9281008961,"name":"Geal-charn Mor","number":"C111","range":"None"},{"Translation":null,"gridref":"NG 513 300","height":775.0,"lat":57.2926610664,"lon":-6.1353632126,"name":"Glamaig - Sgurr Mhairi","number":"C233","range":"None"},{"Translation":null,"gridref":"NC 254 265","height":776.0,"lat":58.1926527249,"lon":-4.9742524782,"name":"Glas Bheinn","number":"C227","range":"None"},{"Translation":null,"gridref":"NN 258 641","height":792.0,"lat":56.7359219907,"lon":-4.8513827616,"name":"Glas Bheinn","number":"C064","range":"None"},{"Translation":"Big greenish-grey hill","gridref":"NN 153 429","height":997.0,"lat":56.541688,"lon":-5.0056662,"name":"Glas Bheinn Mhor","number":"M145","range":"Loch Etive"},{"Translation":"Greenish grey bare hill","gridref":"NO 167 765","height":1068.0,"lat":56.872392,"lon":-3.3682007,"name":"Glas Maol","number":"M069","range":"None"},{"Translation":"From glas-thulchan, green hills","gridref":"NO 051 760","height":1051.0,"lat":56.865673,"lon":-3.5582428,"name":"Glas Tulaichean","number":"M080","range":"None"},{"Translation":"Possibly uproar or noise","gridref":"NH 039 053","height":1035.0,"lat":57.096756,"lon":-5.2387439,"name":"Gleouraich","number":"M097","range":"None"},{"Translation":null,"gridref":"NR 991 415","height":874.0,"lat":55.6254598263,"lon":-5.1951712776,"name":"Goatfell [Goat Fell]","number":"C239","range":"None"},{"Translation":"Gaelic gaorr (filth) or gaoir (noise)","gridref":"NN 002 875","height":987.0,"lat":56.935528,"lon":-5.2855839,"name":"Gulvain","number":"M161","range":"Glenfinnan"},{"Translation":null,"gridref":"NT 113 135","height":808.0,"lat":55.4073802489,"lon":-3.4026331514,"name":"Hart Fell","number":"C009","range":"None"},{"Translation":null,"gridref":"NX 420 869","height":786.8,"lat":55.1511480625,"lon":-4.4822756695,"name":"Kirriereoch Hill","number":"C002","range":"None"},{"Translation":"Hoof or claw hill","gridref":"NG 823 039","height":1020.0,"lat":57.074496,"lon":-5.5933312,"name":"Ladhar Bheinn","number":"M111","range":"None"},{"Translation":null,"gridref":"NN 821 858","height":911.7,"lat":56.948388428,"lon":-3.9404548913,"name":"Leathad an Taobhain","number":"C075","range":"None"},{"Translation":null,"gridref":"NN 330 641","height":906.4,"lat":56.7385554749,"lon":-4.7336017347,"name":"Leum Uilleim","number":"C060","range":"None"},{"Translation":null,"gridref":"NH 429 644","height":763.0,"lat":57.6420556856,"lon":-4.6351071144,"name":"Little Wyvis","number":"C214","range":"None"},{"Translation":"Little loch of the noisy sound (Lochan na Gaire)","gridref":"NO 243 861","height":1155.0,"lat":56.959915,"lon":-3.2464249,"name":"Lochnagar","number":"M021","range":"White Mounth"},{"Translation":"Hill of anger, or hill of mirth or melody","gridref":"NG 869 007","height":939.0,"lat":57.047955,"lon":-5.5148869,"name":"Luinne Bheinne","number":"M234","range":"None"},{"Translation":"Big ridge stretching into the plain","gridref":"NH 065 404","height":986.0,"lat":57.41266,"lon":-5.2232997,"name":"Lurg Mhor","number":"M163","range":"None"},{"Translation":"Hill of the barns","gridref":"NH 120 253","height":1181.0,"lat":57.279531,"lon":-5.1203653,"name":"Mam Sodhail","number":"M014","range":"Glen Affric"},{"Translation":null,"gridref":"NN 115 625","height":796.0,"lat":56.7160102846,"lon":-5.0841284016,"name":"Mam na Gualainn","number":"C063","range":"None"},{"Translation":"Bare hill of the wet place","gridref":"NH 135 458","height":1005.0,"lat":57.46402,"lon":-5.1110655,"name":"Maoile Lunndaidh","number":"M127","range":"None"},{"Translation":"Bald red head","gridref":"NG 924 499","height":933.0,"lat":57.49162,"lon":-5.4656416,"name":"Maol Chean-dearg","number":"M247","range":"None"},{"Translation":"Bald red head","gridref":"NH 032 087","height":981.0,"lat":57.126951,"lon":-5.252952,"name":"Maol Chinn-dearg","number":"M168","range":"South Glen Shiel; Glen Shiel"},{"Translation":"Meaning obscure","gridref":"NO 240 737","height":928.0,"lat":56.848499,"lon":-3.2476366,"name":"Mayar","number":"M253","range":"None"},{"Translation":null,"gridref":"NN 426 449","height":908.2,"lat":56.5695805426,"lon":-4.5648081539,"name":"Meall Buidhe","number":"C032","range":"None"},{"Translation":"Yellow hill","gridref":"NM 849 989","height":946.0,"lat":57.030888,"lon":-5.5462484,"name":"Meall Buidhe","number":"M222","range":"None"},{"Translation":"Yellow hill","gridref":"NN 498 499","height":932.0,"lat":56.616815,"lon":-4.449246,"name":"Meall Buidhe","number":"M248","range":"Loch an Daimh"},{"Translation":"Hill of the quaich","gridref":"NN 716 878","height":951.0,"lat":56.963544,"lon":-4.1133474,"name":"Meall Chuaich","number":"M214","range":"None"},{"Translation":null,"gridref":"NN 174 951","height":826.0,"lat":57.0108139292,"lon":-5.0111255786,"name":"Meall Coire nan Saobhaidh","number":"C159","range":"None"},{"Translation":"Notched, prickly hill","gridref":"NN 615 410","height":1069.0,"lat":56.540526,"lon":-4.2539979,"name":"Meall Corranaich","number":"M068","range":"Lawers Range"},{"Translation":"Red hill","gridref":"NN 161 583","height":953.0,"lat":56.680162,"lon":-5.0036323,"name":"Meall Dearg (Aonach Eagach)","number":"M212","range":"Glen Coe; Aonach Eagach"},{"Translation":null,"gridref":"NH 245 078","height":789.0,"lat":57.1275076423,"lon":-4.9030196024,"name":"Meall Dubh","number":"C161","range":"None"},{"Translation":"Rough hill","gridref":"NN 647 517","height":968.0,"lat":56.637514,"lon":-4.2075966,"name":"Meall Garbh","number":"M186","range":"Carn Mairg"},{"Translation":"Rough hill","gridref":"NN 644 436","height":1118.0,"lat":56.564713,"lon":-4.2082354,"name":"Meall Garbh","number":"M035","range":"Lawers Range"},{"Translation":"Gaelic gairdean, meaning a shoulder, arm, hand","gridref":"NN 514 397","height":1039.0,"lat":56.525772,"lon":-4.4173482,"name":"Meall Ghaordie","number":"M093","range":"None"},{"Translation":"Greenish-grey hill","gridref":"NN 431 321","height":959.0,"lat":56.454865,"lon":-4.5475529,"name":"Meall Glas","number":"M199","range":"Loch Lochay; Crianlarich"},{"Translation":"Blue hill","gridref":"NH 221 696","height":949.0,"lat":57.680966,"lon":-4.9853505,"name":"Meall Gorm","number":"M215","range":"Loch Fannich"},{"Translation":"Hill of horse studs","gridref":"NN 674 438","height":1001.0,"lat":56.567366,"lon":-4.1595582,"name":"Meall Greigh","number":"M136","range":"Lawers Range"},{"Translation":null,"gridref":"NC 352 449","height":777.0,"lat":58.3614813629,"lon":-4.8205378743,"name":"Meall Horn","number":"C220","range":"None"},{"Translation":null,"gridref":"NN 094 528","height":772.0,"lat":56.62814443,"lon":-5.1112662361,"name":"Meall Lighiche","number":"C053","range":"None"},{"Translation":null,"gridref":"NN 807 543","height":787.0,"lat":56.6652140363,"lon":-3.948728431,"name":"Meall Tairneachan","number":"C036","range":"None"},{"Translation":null,"gridref":"NO 110 673","height":794.0,"lat":56.788715426,"lon":-3.4587215425,"name":"Meall Uaine","number":"C086","range":"None"},{"Translation":"Hill of the grey corrie","gridref":"NN 612 439","height":926.0,"lat":56.566471,"lon":-4.2604246,"name":"Meall a Choire Leith","number":"M261","range":"Lawers Range"},{"Translation":"Hill of the bellowing (of stags)","gridref":"NN 250 503","height":1108.0,"lat":56.611799,"lon":-4.8531271,"name":"Meall a' Bhuiridh","number":"M045","range":"Loch Etive"},{"Translation":"Hill of the crossing","gridref":"NH 184 733","height":934.0,"lat":57.712675,"lon":-5.0500969,"name":"Meall a' Chrasgaidh","number":"M243","range":"Loch Fannich"},{"Translation":null,"gridref":"NH 990 115","height":810.0,"lat":57.1831568387,"lon":-3.6729043504,"name":"Meall a'Bhuachaille","number":"C093","range":"None"},{"Translation":null,"gridref":"NG 976 634","height":887.0,"lat":57.6150263077,"lon":-5.3935868515,"name":"Meall a'Ghiubhais [Meall a'Ghiuthais]","number":"C190","range":"None"},{"Translation":null,"gridref":"NN 029 854","height":774.0,"lat":56.9178537078,"lon":-5.2425029321,"name":"Meall a'Phubuill","number":"C168","range":"None"},{"Translation":null,"gridref":"NN 270 192","height":764.0,"lat":56.3334786871,"lon":-4.8017727293,"name":"Meall an Fhudair","number":"C026","range":"None"},{"Translation":null,"gridref":"NN 542 234","height":852.0,"lat":56.3803373717,"lon":-4.3638653831,"name":"Meall an t-Seallaidh","number":"C017","range":"None"},{"Translation":null,"gridref":"NN 650 186","height":809.0,"lat":56.3404532411,"lon":-4.1864159253,"name":"Meall na Fearna","number":"C014","range":"None"},{"Translation":null,"gridref":"NN 640 702","height":777.3,"lat":56.8033866067,"lon":-4.2297321699,"name":"Meall na Leitreach","number":"C072","range":"None"},{"Translation":"Hill of the tongue","gridref":"NN 220 924","height":918.0,"lat":56.988384,"lon":-4.9312908,"name":"Meall na Teanga","number":"M276","range":"Loch Lochy"},{"Translation":null,"gridref":"NH 515 000","height":862.0,"lat":57.0670238784,"lon":-4.4520328144,"name":"Meall na h-Aisre","number":"C110","range":"None"},{"Translation":null,"gridref":"NN 185 946","height":838.0,"lat":57.0067622359,"lon":-4.992635733,"name":"Meall na h-Eilde","number":"C158","range":"None"},{"Translation":null,"gridref":"NN 586 435","height":778.9,"lat":56.5621071553,"lon":-4.3034971212,"name":"Meall nam Maigheach","number":"C046","range":"None"},{"Translation":"Big rock","gridref":"NN 694 496","height":981.0,"lat":56.619997,"lon":-4.1299642,"name":"Meall nan Aighean","number":"M169","range":"Carn Mairg"},{"Translation":"Ceap, meaning a back or hilltop","gridref":"NH 257 825","height":977.0,"lat":57.798093,"lon":-4.9344288,"name":"Meall nan Ceapraichean","number":"M177","range":"None"},{"Translation":"Hill of the birds","gridref":"NN 192 449","height":928.0,"lat":56.561149,"lon":-4.9437239,"name":"Meall nan Eun","number":"M254","range":"Loch Etive"},{"Translation":null,"gridref":"NN 460 397","height":806.0,"lat":56.5240370534,"lon":-4.506350394,"name":"Meall nan Subh","number":"C045","range":"Loch Lochay; Crianlarich"},{"Translation":"Hill of the ptarmigan","gridref":"NN 585 390","height":1044.0,"lat":56.521679,"lon":-4.3016525,"name":"Meall nan Tarmachan","number":"M089","range":"None"},{"Translation":null,"gridref":"NN 776 908","height":769.0,"lat":56.9921080128,"lon":-4.0168818086,"name":"Meallach Mhor","number":"C080","range":"None"},{"Translation":null,"gridref":"NC 357 391","height":801.0,"lat":58.3096400892,"lon":-4.8078458836,"name":"Meallan Liath Coire Mhic Dhughaill","number":"C217","range":"None"},{"Translation":null,"gridref":"NH 263 544","height":838.0,"lat":57.5462550821,"lon":-4.9061773407,"name":"Meallan nan Uan","number":"C181","range":"None"},{"Translation":null,"gridref":"NX 427 855","height":843.0,"lat":55.1388024292,"lon":-4.4705073829,"name":"Merrick","number":"C001","range":"None"},{"Translation":"Big hill","gridref":"NN 938 942","height":1113.0,"lat":57.026644,"lon":-3.7511481,"name":"Monadh Mor","number":"M040","range":"Cairngorms"},{"Translation":null,"gridref":"NO 176 706","height":807.0,"lat":56.8195688357,"lon":-3.3517347489,"name":"Monamenach","number":"C089","range":"None"},{"Translation":null,"gridref":"NO 132 886","height":859.0,"lat":56.9804180429,"lon":-3.4299955876,"name":"Morrone","number":"C083","range":"None"},{"Translation":"Big water","gridref":"NH 101 499","height":928.0,"lat":57.499382,"lon":-5.1708417,"name":"Moruisg","number":"M255","range":"None"},{"Translation":null,"gridref":"NJ 376 039","height":871.0,"lat":57.1217810709,"lon":-3.0322833812,"name":"Morven","number":"C102","range":"None"},{"Translation":null,"gridref":"NO 549 844","height":778.0,"lat":56.9486504684,"lon":-2.7430378453,"name":"Mount Battock","number":"C091","range":"None"},{"Translation":"Gaelic monadh, meaning hill","gridref":"NO 409 869","height":939.0,"lat":56.969523,"lon":-2.9736956,"name":"Mount Keen","number":"M235","range":"Cairngorms"},{"Translation":"Summit of the stone of the plain","gridref":"NN 883 927","height":1019.0,"lat":57.011877,"lon":-3.8410362,"name":"Mullach Clach a' Bhlair","number":"M114","range":"Cairngorms"},{"Translation":"Summit of the corrie of Farquhar's son","gridref":"NH 052 735","height":1018.0,"lat":57.708942,"lon":-5.2714419,"name":"Mullach Coire Mhic Fhearchair","number":"M115","range":"Fisherfield Forest"},{"Translation":"Heather-corrie peak","gridref":"NH 095 171","height":1102.0,"lat":57.204948,"lon":-5.1554702,"name":"Mullach Fraoch-choire","number":"M049","range":"None"},{"Translation":"Summit of the row of pinnacles","gridref":"NG 912 577","height":1023.0,"lat":57.561002,"lon":-5.4923096,"name":"Mullach an Rathain (Liathach)","number":"M108","range":"None"},{"Translation":"Summit of the corries","gridref":"NN 122 662","height":939.0,"lat":56.749481,"lon":-5.0729728,"name":"Mullach na Coirean","number":"M236","range":"Mamores"},{"Translation":"Perhaps summit of the hawk","gridref":"NH 080 259","height":982.0,"lat":57.283249,"lon":-5.1870709,"name":"Mullach na Dheiragain","number":"M167","range":"None"},{"Translation":"The maidens","gridref":"NN 203 652","height":1056.0,"lat":56.743701,"lon":-4.9400028,"name":"Na Gruagaichean","number":"M074","range":"Mamores"},{"Translation":null,"gridref":"NC 209 292","height":809.0,"lat":58.215064543,"lon":-5.0529444427,"name":"Quinag - Sail Gharbh","number":"C224","range":"None"},{"Translation":null,"gridref":"NC 198 304","height":776.0,"lat":58.2253785181,"lon":-5.0726163558,"name":"Quinag - Sail Gorm [Sail Ghorm]","number":"C226","range":"None"},{"Translation":null,"gridref":"NC 206 277","height":764.0,"lat":58.2014894683,"lon":-5.0568956865,"name":"Quinag - Spidean Coinich","number":"C228","range":"None"},{"Translation":null,"gridref":"NM 756 778","height":882.0,"lat":56.8373070451,"lon":-5.6846253029,"name":"Rois-Bheinn","number":"C122","range":"None"},{"Translation":null,"gridref":"NH 018 756","height":918.7,"lat":57.7262899137,"lon":-5.3332622165,"name":"Ruadh Stac Mor","number":"C200","range":"None"},{"Translation":"Big red peak","gridref":"NH 018 756","height":919.0,"lat":57.726287,"lon":-5.3301335,"name":"Ruadh Stac Mor","number":"M273","range":"Fisherfield Forest"},{"Translation":null,"gridref":"NG 972 613","height":896.0,"lat":57.5960169006,"lon":-5.3985260603,"name":"Ruadh-stac Beag","number":"C189","range":"None"},{"Translation":"Hill of the rowan","gridref":"NH 133 154","height":1002.0,"lat":57.191263,"lon":-5.0913888,"name":"Sail Chaorainn","number":"M133","range":"None"},{"Translation":null,"gridref":"NH 032 887","height":767.0,"lat":57.8443741523,"lon":-5.3205345246,"name":"Sail Mhor","number":"C208","range":"None"},{"Translation":"Little heel","gridref":"NH 017 148","height":956.0,"lat":57.181012,"lon":-5.2825346,"name":"Saileag","number":"M205","range":"Glen Shiel; Brothers Ridge"},{"Translation":"The fairly hill of the Caledonians","gridref":"NN 713 547","height":1083.0,"lat":56.666309,"lon":-4.10157,"name":"Schiehallion","number":"M059","range":"None"},{"Translation":"Old upper part","gridref":"NH 281 878","height":926.0,"lat":57.846565,"lon":-4.8979217,"name":"Seana Bhraigh","number":"M262","range":"None"},{"Translation":"Big stony hillside","gridref":"NN 598 731","height":991.0,"lat":56.828167,"lon":-4.2991204,"name":"Sgairneach Mhor","number":"M155","range":"None"},{"Translation":"Back wing","gridref":"NN 462 317","height":921.0,"lat":56.452296,"lon":-4.4970693,"name":"Sgiath Chuil","number":"M270","range":"Loch Lochay; Crianlarich"},{"Translation":"Goat's peak","gridref":"NN 444 674","height":955.0,"lat":56.772112,"lon":-4.5477415,"name":"Sgor Gaibhre","number":"M208","range":"Loch Ossian"},{"Translation":"Peak of wind","gridref":"NN 902 989","height":1118.0,"lat":57.068,"lon":-3.8124757,"name":"Sgor Gaoith","number":"M036","range":"Cairngorms"},{"Translation":null,"gridref":"NO 115 825","height":887.0,"lat":56.9253150121,"lon":-3.4558316393,"name":"Sgor Mor","number":"C082","range":"None"},{"Translation":null,"gridref":"NO 007 914","height":813.0,"lat":57.0030423318,"lon":-3.6367950732,"name":"Sgor Mor","number":"C092","range":"None"},{"Translation":"Peak of the little green loch","gridref":"NN 954 976","height":1258.0,"lat":57.057539,"lon":-3.7262195,"name":"Sgor an Lochan Uaine","number":"M005","range":"Cairngorms; Braeriach"},{"Translation":"Peak of the treasure","gridref":"NN 111 518","height":994.0,"lat":56.619859,"lon":-5.0803589,"name":"Sgor na h-Ulaidh","number":"M149","range":"Glen Coe"},{"Translation":null,"gridref":"NM 895 757","height":775.0,"lat":56.8249798095,"lon":-5.4547634723,"name":"Sgorr Craobh a'Chaorainn","number":"C133","range":"None"},{"Translation":"Red peak","gridref":"NN 056 558","height":1024.0,"lat":56.65349,"lon":-5.1728596,"name":"Sgorr Dhearg (Beinn a' Bheithir)","number":"M107","range":"Glen Coe"},{"Translation":"Donald's peak","gridref":"NN 040 555","height":1001.0,"lat":56.650131,"lon":-5.1986865,"name":"Sgorr Dhonuill (Beinn a' Bheithir)","number":"M137","range":"Glen Coe"},{"Translation":"Red peak","gridref":"NG 959 505","height":962.0,"lat":57.49859,"lon":-5.4078617,"name":"Sgorr Ruadh","number":"M195","range":"None"},{"Translation":null,"gridref":"NH 281 362","height":818.0,"lat":57.383665241,"lon":-4.8632515967,"name":"Sgorr na Diollaid","number":"C187","range":"None"},{"Translation":"Peak of the Fian warriors","gridref":"NN 140 583","height":967.0,"lat":56.679332,"lon":-5.0378588,"name":"Sgorr nam Fiannaidh (Aonach Eagach)","number":"M188","range":"Glen Coe; Aonach Eagach"},{"Translation":null,"gridref":"NG 969 531","height":871.0,"lat":57.5223557274,"lon":-5.3966742772,"name":"Sgorr nan Lochan Uaine","number":"C197","range":"None"},{"Translation":null,"gridref":"NG 977 303","height":879.0,"lat":57.3182647734,"lon":-5.3644313302,"name":"Sguman Coinntich","number":"C185","range":"None"},{"Translation":"Alexander's peak (after Sherriff Alexander Nicholson)","gridref":"NG 450 207","height":992.0,"lat":57.205873,"lon":-6.2241087,"name":"Sgurr Alasdair","number":"M154","range":"Black Cuilin"},{"Translation":"White peak","gridref":"NH 055 745","height":989.0,"lat":57.71804,"lon":-5.2672243,"name":"Sgurr Ban (Letterewe)","number":"M157","range":"Fisherfield Forest"},{"Translation":"Speckled peak","gridref":"NH 158 711","height":999.0,"lat":57.691885,"lon":-5.0919861,"name":"Sgurr Breac","number":"M138","range":"Loch Fannich"},{"Translation":"Moss peak","gridref":"NH 076 446","height":999.0,"lat":57.450795,"lon":-5.208316,"name":"Sgurr Choinnich","number":"M139","range":"None"},{"Translation":"Big peak of the moss","gridref":"NN 227 714","height":1094.0,"lat":56.800247,"lon":-4.9051141,"name":"Sgurr Choinnich Mor","number":"M052","range":"Grey Corries"},{"Translation":null,"gridref":"NG 790 010","height":796.0,"lat":57.0469291873,"lon":-5.6491680816,"name":"Sgurr Coire Choinnichean","number":"C155","range":"None"},{"Translation":null,"gridref":"NM 947 946","height":835.0,"lat":56.9967956836,"lon":-5.3848221961,"name":"Sgurr Cos na Breachd-laoidh","number":"C154","range":"None"},{"Translation":"Red peak","gridref":"NG 444 215","height":986.0,"lat":57.212705,"lon":-6.2348352,"name":"Sgurr Dearg (The Inaccessible Pinnacle)","number":"M164","range":"Black Cuilin"},{"Translation":null,"gridref":"NM 889 678","height":888.0,"lat":56.7538672451,"lon":-5.4580566619,"name":"Sgurr Dhomhnuill","number":"C127","range":"None"},{"Translation":null,"gridref":"NG 979 557","height":782.0,"lat":57.5461169649,"lon":-5.3821252544,"name":"Sgurr Dubh","number":"C199","range":"None"},{"Translation":"Big black peak","gridref":"NG 457 205","height":944.0,"lat":57.20447,"lon":-6.2123489,"name":"Sgurr Dubh Mor","number":"M228","range":"Black Cuilin"},{"Translation":"Big peak of the hind","gridref":"NN 230 657","height":1010.0,"lat":56.74922,"lon":-4.8962632,"name":"Sgurr Eilde Mor","number":"M123","range":"Mamores"},{"Translation":"Peak of the cold hollow","gridref":"NH 235 437","height":1049.0,"lat":57.449182,"lon":-4.9430838,"name":"Sgurr Fhuar-thuill","number":"M082","range":"Strathfarrar"},{"Translation":"Obscure","gridref":"NG 978 166","height":1067.0,"lat":57.195452,"lon":-5.3483982,"name":"Sgurr Fhuaran","number":"M070","range":"Glen Shiel; Five Sisters of Kintail"},{"Translation":"Light coloured peak, or perhaps peak of wine","gridref":"NH 064 837","height":1060.0,"lat":57.80093,"lon":-5.2595692,"name":"Sgurr Fiona (An Teallach)","number":"M073","range":"None"},{"Translation":null,"gridref":"NH 035 218","height":839.0,"lat":57.2445692123,"lon":-5.2612538713,"name":"Sgurr Gaorsaic","number":"C171","range":"None"},{"Translation":null,"gridref":"NM 875 751","height":849.0,"lat":56.8186900201,"lon":-5.4870685288,"name":"Sgurr Ghiubhsachain","number":"C130","range":"None"},{"Translation":null,"gridref":"NN 290 748","height":809.0,"lat":56.8331149977,"lon":-4.8062119905,"name":"Sgurr Innse","number":"C062","range":"Loch Treig"},{"Translation":null,"gridref":"NG 917 173","height":779.0,"lat":57.1990009494,"lon":-5.4531994939,"name":"Sgurr Mhic Bharraich","number":"C144","range":"None"},{"Translation":"MacKenzie's peak (after John MacKenzie, Cuillin guide)","gridref":"NG 450 210","height":948.0,"lat":57.20856,"lon":-6.2244163,"name":"Sgurr Mhic Choinnich","number":"M217","range":"Black Cuilin"},{"Translation":"Possibly jewelled hill","gridref":"NG 865 613","height":986.0,"lat":57.591081,"lon":-5.5738763,"name":"Sgurr Mhor (Beinn Alligin)","number":"M162","range":"None"},{"Translation":null,"gridref":"NN 012 944","height":880.0,"lat":56.9978451413,"lon":-5.2775550034,"name":"Sgurr Mhurlagain","number":"C151","range":"None"},{"Translation":"Big peak","gridref":"NM 965 980","height":1003.0,"lat":57.028079,"lon":-5.3547477,"name":"Sgurr Mor","number":"M132","range":"None"},{"Translation":"Big peak","gridref":"NH 203 718","height":1110.0,"lat":57.699984,"lon":-5.0171332,"name":"Sgurr Mor","number":"M043","range":"Loch Fannich"},{"Translation":"Peak of the rounded hillock","gridref":"NM 939 879","height":963.0,"lat":56.936354,"lon":-5.3892554,"name":"Sgurr Thuilm","number":"M193","range":"Glenfinnan"},{"Translation":"Peak of the red pass","gridref":"NH 035 143","height":1036.0,"lat":57.177303,"lon":-5.2524139,"name":"Sgurr a' Bhealaich Dheirg","number":"M096","range":"Glen Shiel; Brothers Ridge"},{"Translation":"Peak of the little field of the berries","gridref":"NH 087 447","height":1053.0,"lat":57.452156,"lon":-5.1900933,"name":"Sgurr a' Chaorachain","number":"M078","range":"None"},{"Translation":"Peak of the greenish-grey corrie","gridref":"NH 259 430","height":1083.0,"lat":57.443829,"lon":-4.9026481,"name":"Sgurr a' Choire Ghlais","number":"M060","range":"Strathfarrar"},{"Translation":"Peak of torment, anxiety","gridref":"NG 445 232","height":973.0,"lat":57.22799,"lon":-6.2349317,"name":"Sgurr a' Ghreadhaidh","number":"M185","range":"Black Cuilin"},{"Translation":"Peak of the fox","gridref":"NG 446 235","height":918.0,"lat":57.230733,"lon":-6.2335884,"name":"Sgurr a' Mhadaidh","number":"M277","range":"Black Cuilin"},{"Translation":"Peak of the large rounded hill","gridref":"NN 164 667","height":1099.0,"lat":56.755639,"lon":-5.004751,"name":"Sgurr a' Mhaim","number":"M051","range":"Mamores"},{"Translation":"Peak of the shellfish","gridref":"NG 983 065","height":1027.0,"lat":57.105097,"lon":-5.331977,"name":"Sgurr a' Mhaoraich","number":"M104","range":"None"},{"Translation":null,"gridref":"NG 958 110","height":885.2,"lat":57.1443514252,"lon":-5.3800874693,"name":"Sgurr a'Bhac Chaolais","number":"C141","range":"None"},{"Translation":null,"gridref":"NG 796 417","height":792.0,"lat":57.4120765488,"lon":-5.675528138,"name":"Sgurr a'Chaorachain","number":"C198","range":"None"},{"Translation":null,"gridref":"NG 895 015","height":913.32,"lat":57.0563258706,"lon":-5.4763007018,"name":"Sgurr a'Choire-bheithe","number":"C146","range":"None"},{"Translation":null,"gridref":"NH 264 557","height":879.0,"lat":57.5579556363,"lon":-4.9054359794,"name":"Sgurr a'Mhuilinn","number":"C176","range":"None"},{"Translation":null,"gridref":"NG 940 227","height":841.0,"lat":57.2484617893,"lon":-5.4195837856,"name":"Sgurr an Airgid","number":"C170","range":"None"},{"Translation":"Peak of the broad thicket","gridref":"NH 015 099","height":1010.0,"lat":57.136982,"lon":-5.2819386,"name":"Sgurr an Doire Leathain","number":"M122","range":"South Glen Shiel; Glen Shiel"},{"Translation":null,"gridref":"NM 987 979","height":901.0,"lat":57.0281509628,"lon":-5.3215552373,"name":"Sgurr an Fhuarain","number":"C147","range":"None"},{"Translation":"Peak of the little loch","gridref":"NH 005 104","height":1004.0,"lat":57.141033,"lon":-5.2988323,"name":"Sgurr an Lochain","number":"M131","range":"South Glen Shiel; Glen Shiel"},{"Translation":null,"gridref":"NM 885 839","height":796.0,"lat":56.8980548738,"lon":-5.4780092761,"name":"Sgurr an Utha","number":"C166","range":"None"},{"Translation":null,"gridref":"NM 770 777","height":874.0,"lat":56.8370843156,"lon":-5.6615613609,"name":"Sgurr na Ba Glaise","number":"C123","range":"None"},{"Translation":"Perhaps from banachdag, a milkmaid","gridref":"NG 440 224","height":965.0,"lat":57.220544,"lon":-6.242366,"name":"Sgurr na Banachdich","number":"M190","range":"Black Cuilin"},{"Translation":"Stony peak","gridref":"NG 977 158","height":1002.0,"lat":57.188234,"lon":-5.3494,"name":"Sgurr na Carnach","number":"M134","range":"Glen Shiel; Five Sisters of Kintail"},{"Translation":"Peak of the breast","gridref":"NM 902 966","height":1040.0,"lat":57.012704,"lon":-5.4571761,"name":"Sgurr na Ciche","number":"M092","range":"None"},{"Translation":"Peak of the black chest","gridref":"NG 984 149","height":1027.0,"lat":57.180471,"lon":-5.33711,"name":"Sgurr na Ciste Duibhe","number":"M105","range":"Glen Shiel; Five Sisters of Kintail"},{"Translation":null,"gridref":"NH 055 453","height":863.0,"lat":57.456181,"lon":-5.2466899992,"name":"Sgurr na Feartaig","number":"C179","range":"None"},{"Translation":"Peak of the bog","gridref":"NH 160 351","height":1150.0,"lat":57.369064,"lon":-5.0614259,"name":"Sgurr na Lapaich","number":"M024","range":"Loch Mullardoch"},{"Translation":"Peak of the redness","gridref":"NH 288 426","height":993.0,"lat":57.441343,"lon":-4.8541152,"name":"Sgurr na Ruaidhe","number":"M151","range":"Strathfarrar"},{"Translation":"Peak of the knife","gridref":"NG 946 113","height":946.0,"lat":57.146503,"lon":-5.3968915,"name":"Sgurr na Sgine","number":"M223","range":"South Glen Shiel; Glen Shiel"},{"Translation":null,"gridref":"NH 087 480","height":913.43,"lat":57.4817562076,"lon":-5.1954234301,"name":"Sgurr nan Ceannaichean","number":"C175","range":"None"},{"Translation":"Peak of the quarters","gridref":"NH 057 228","height":1151.0,"lat":57.254474,"lon":-5.2227294,"name":"Sgurr nan Ceathreamhnan","number":"M022","range":"None"},{"Translation":"Peak of the white stones","gridref":"NH 184 715","height":1093.0,"lat":57.69653,"lon":-5.0487387,"name":"Sgurr nan Clach Geala","number":"M053","range":"Loch Fannich"},{"Translation":"Peak of the corries","gridref":"NM 933 958","height":953.0,"lat":57.006929,"lon":-5.4055638,"name":"Sgurr nan Coireachan","number":"M213","range":"None"},{"Translation":"Peak of the corries","gridref":"NM 902 880","height":956.0,"lat":56.935589,"lon":-5.4500305,"name":"Sgurr nan Coireachean","number":"M206","range":"Glenfinnan"},{"Translation":"Peak of the keeper of the hounds","gridref":"NH 129 138","height":1109.0,"lat":57.176748,"lon":-5.0967955,"name":"Sgurr nan Conbhairean","number":"M044","range":"None"},{"Translation":"Peak of the horses","gridref":"NH 184 697","height":923.0,"lat":57.680385,"lon":-5.0473818,"name":"Sgurr nan Each","number":"M267","range":"Loch Fannich"},{"Translation":"Peak of the notches","gridref":"NG 457 195","height":924.0,"lat":57.195511,"lon":-6.2113271,"name":"Sgurr nan Eag","number":"M265","range":"Black Cuilin"},{"Translation":null,"gridref":"NG 927 048","height":898.0,"lat":57.0873676246,"lon":-5.426218483,"name":"Sgurr nan Eugallt","number":"C148","range":"None"},{"Translation":null,"gridref":"NG 931 044","height":895.0,"lat":57.0839607159,"lon":-5.4192796311,"name":"Sgurr nan Eugallt East Top","number":"C149","range":"None"},{"Translation":"Peak of the young men","gridref":"NG 471 252","height":964.0,"lat":57.247351,"lon":-6.1940225,"name":"Sgurr nan Gillean","number":"M191","range":"Black Cuilin"},{"Translation":null,"gridref":"NX 407 905","height":774.1,"lat":55.1830497167,"lon":-4.5047151101,"name":"Shalloch on Minnoch","number":"C004","range":"None"},{"Translation":"Gaelic sleacgh, a spear","gridref":"NH 004 690","height":981.0,"lat":57.666486,"lon":-5.3481282,"name":"Slioch - North Top","number":"M170","range":"None"},{"Translation":"Peak of the stony corrie","gridref":"NG 966 597","height":993.0,"lat":57.581397,"lon":-5.4038937,"name":"Spidean Coire nan Clach (Beinn Eighe)","number":"M150","range":"None"},{"Translation":"Peak of deer, or other wild animals","gridref":"NH 066 043","height":996.0,"lat":57.08893,"lon":-5.1934811,"name":"Spidean Mialach","number":"M146","range":"None"},{"Translation":"Peak of the grey corrie","gridref":"NG 929 579","height":1055.0,"lat":57.563578,"lon":-5.4641195,"name":"Spidean a Choire Leith (Liathach)","number":"M075","range":"None"},{"Translation":"Nose of the rough corrie","gridref":"NN 222 945","height":937.0,"lat":57.007301,"lon":-4.9294853,"name":"Sron a' Choire Ghairbh","number":"M239","range":"Loch Lochy"},{"Translation":null,"gridref":"NN 456 453","height":837.0,"lat":56.5741671393,"lon":-4.5161948817,"name":"Sron a'Choire Chnapanich [Sron a'Choire Chnapanaich]","number":"C034","range":"None"},{"Translation":"White peak","gridref":"NN 147 654","height":999.0,"lat":56.743304,"lon":-5.0315735,"name":"Stob Ban","number":"M140","range":"Mamores"},{"Translation":"White peak","gridref":"NN 266 723","height":977.0,"lat":56.809791,"lon":-4.8419485,"name":"Stob Ban","number":"M178","range":"Grey Corries"},{"Translation":"Gaelic binnein, meaning peak","gridref":"NN 434 227","height":1165.0,"lat":56.370597,"lon":-4.5370658,"name":"Stob Binnein","number":"M018","range":"Loch Lomond; Crianlarich"},{"Translation":"Gaelic clamhras, meaning brawling or clamouring","gridref":"NN 262 738","height":1177.0,"lat":56.823101,"lon":-4.8495136,"name":"Stob Choire Claurigh","number":"M015","range":"Grey Corries"},{"Translation":"Peak of the corrie of the Scotsmen","gridref":"NN 169 443","height":1044.0,"lat":56.554874,"lon":-4.9806708,"name":"Stob Coir an Albannaich","number":"M090","range":"Loch Etive"},{"Translation":null,"gridref":"NN 230 109","height":817.0,"lat":56.2575244934,"lon":-4.8609300538,"name":"Stob Coire Creagach [Binnein an Fhidhleir]","number":"C025","range":"None"},{"Translation":"Peak of the corrie of the little waterfall","gridref":"NN 308 730","height":1115.0,"lat":56.817619,"lon":-4.7737085,"name":"Stob Coire Easain","number":"M039","range":"Loch Treig"},{"Translation":"Peak of the dreadful corrie","gridref":"NN 154 536","height":1072.0,"lat":56.637721,"lon":-5.0116741,"name":"Stob Coire Sgreamach","number":"M065","range":"Glen Coe"},{"Translation":"Peak of the corrie of the scree","gridref":"NN 356 743","height":979.0,"lat":56.831007,"lon":-4.6960063,"name":"Stob Coire Sgriodain","number":"M174","range":"Loch Treig"},{"Translation":"Peak of the corrie of the cairn","gridref":"NN 185 660","height":981.0,"lat":56.750182,"lon":-4.9699579,"name":"Stob Coire a' Chairn","number":"M171","range":"Mamores"},{"Translation":null,"gridref":"NN 016 726","height":771.0,"lat":56.802496782,"lon":-5.253862439,"name":"Stob Coire a'Chearcaill","number":"C134","range":"None"},{"Translation":"Peak of the corrie of the calf","gridref":"NN 239 725","height":1116.0,"lat":56.810572,"lon":-4.88625,"name":"Stob Coire an Laoigh","number":"M038","range":"Grey Corries"},{"Translation":"Peak of the stag","gridref":"NN 094 308","height":998.0,"lat":56.430785,"lon":-5.0926196,"name":"Stob Daimh","number":"M143","range":"Loch Awe"},{"Translation":null,"gridref":"NN 166 488","height":883.0,"lat":56.5951328709,"lon":-4.9909574199,"name":"Stob Dubh","number":"C055","range":"None"},{"Translation":"Goat peak","gridref":"NN 230 455","height":1090.0,"lat":56.56798,"lon":-4.8823866,"name":"Stob Ghabhar","number":"M055","range":"Loch Etive"},{"Translation":"Peak of the pot of the high corrie","gridref":"NN 428 888","height":1054.0,"lat":56.963624,"lon":-4.5871287,"name":"Stob Poite Coire Ardair","number":"M076","range":"None"},{"Translation":"Peak of the middle corrie","gridref":"NN 316 736","height":1105.0,"lat":56.823293,"lon":-4.7610153,"name":"Stob a' Choire Mheadhoin","number":"M046","range":"Loch Treig"},{"Translation":"Peak of the dun-coloured corrie","gridref":"NN 257 459","height":945.0,"lat":56.572579,"lon":-4.838773,"name":"Stob a' Choire Odhair","number":"M226","range":"Loch Etive"},{"Translation":null,"gridref":"NN 417 159","height":869.0,"lat":56.3090028942,"lon":-4.5618596889,"name":"Stob a'Choin","number":"C016","range":"None"},{"Translation":null,"gridref":"NN 537 694","height":855.0,"lat":56.7930807814,"lon":-4.3980146233,"name":"Stob an Aonaich Mhoir","number":"C069","range":"None"},{"Translation":null,"gridref":"NM 946 863","height":909.0,"lat":56.9223197885,"lon":-5.3797019425,"name":"Streap","number":"C162","range":"None"},{"Translation":"Peak of harm or danger","gridref":"NN 617 174","height":975.0,"lat":56.328725,"lon":-4.238258,"name":"Stuc a' Chroin","number":"M182","range":"Loch Earn"},{"Translation":"Peak of the little loch","gridref":"NN 483 448","height":960.0,"lat":56.570557,"lon":-4.4706735,"name":"Stuchd an Lochain","number":"M197","range":"Loch an Daimh"},{"Translation":null,"gridref":"NN 245 030","height":787.0,"lat":56.1871915066,"lon":-4.8314544497,"name":"The Brack","number":"C029","range":"None"},{"Translation":"From Gaelic Carn Bhalg, hill of bags","gridref":"NO 134 773","height":933.0,"lat":56.878972,"lon":-3.4225932,"name":"The Cairnwell","number":"M245","range":"None"},{"Translation":null,"gridref":"NN 259 058","height":884.0,"lat":56.2128314579,"lon":-4.8107225724,"name":"The Cobbler [Ben Arthur]","number":"C022","range":"Arrochar Alps"},{"Translation":"Penis of the demon","gridref":"NN 976 951","height":1004.0,"lat":57.035585,"lon":-3.6889457,"name":"The Devil's Point","number":"M130","range":"Cairngorms; Braeriach"},{"Translation":null,"gridref":"NN 598 842","height":911.4,"lat":56.9278059985,"lon":-4.3062737334,"name":"The Fara","number":"C065","range":"Ben Alder Forest"},{"Translation":"The Saddle","gridref":"NG 936 131","height":1010.0,"lat":57.162196,"lon":-5.4148769,"name":"The Saddle","number":"M121","range":"South Glen Shiel; Glen Shiel"},{"Translation":null,"gridref":"NN 625 741","height":803.0,"lat":56.8379540568,"lon":-4.2564131126,"name":"The Sow of Atholl [Meall an Dobharchain]","number":"C071","range":"None"},{"Translation":"Rocky hollow","gridref":"NH 194 282","height":1054.0,"lat":57.30853,"lon":-4.9999208,"name":"Toll Creagach","number":"M077","range":"None"},{"Translation":"Doll mounth or hill (leading to Glen Doll)","gridref":"NO 210 800","height":958.0,"lat":56.904579,"lon":-3.2987684,"name":"Tolmount","number":"M202","range":"None"},{"Translation":"Yellow hill","gridref":"NO 213 787","height":957.0,"lat":56.892954,"lon":-3.2934403,"name":"Tom Buidhe","number":"M204","range":"None"},{"Translation":"Hill of the moss","gridref":"NH 164 273","height":1112.0,"lat":57.29926,"lon":-5.0489777,"name":"Tom a' Choinich","number":"M041","range":"None"},{"Translation":"Hill of the maiden","gridref":"NG 859 601","height":922.0,"lat":57.58004,"lon":-5.5828339,"name":"Tom na Gruagaich (Beinn Alligin)","number":"M268","range":"None"},{"Translation":null,"gridref":"NT 163 150","height":821.0,"lat":55.4217348389,"lon":-3.3241063567,"name":"White Coomb","number":"C007","range":"None"}]